Workbook
Name CustomerList: OFFSET(Helpers!$A$2,0,0,COUNTIF(Helpers!$A$2:$A$202,"<>"),1)
Name FilteredCustomerList: OFFSET(Helpers!$C$2,0,0,COUNTIF(Helpers!$C$2:$C$202,"<>"),1)

Sheet Dashboard
A1: ROW Freight Cost Dashboard
B4: Select Customer: | C4: Acostallantas S.A, Colombia
B5: Search Customer:
A6: Top 10 Lowest Cost Combinations
A7: Rank | B7: Region / Geography | C7: POL | D7: POD | E7: Forwarder | F7: Carrier / Line | G7: Incoterm | H7: Origin Cost (USD) | I7: Ocean Freight (USD) | J7: Total Freight (USD)
A8: 1 | B8: =IFERROR(INDEX(Combination!$C$2:$C$2628,$N8),"") -> S.A | C8: =IFERROR(INDEX(Combination!$F$2:$F$2628,$N8),"") -> ICD Dhannad | D8: =IFERROR(INDEX(Combination!$G$2:$G$2628,$N8),"") -> Buenaventura | E8: =IFERROR(INDEX(Combination!$H$2:$H$2628,$N8),"") -> Clearship | F8: =IFERROR(INDEX(Combination!$J$2:$J$2628,$N8),"") -> CMA | G8: =IFERROR(INDEX(Combination!$I$2:$I$2628,$N8),"") -> CIF | H8: =IFERROR(INDEX(Combination!$O$2:$O$2628,$N8),"") -> 0 | I8: =IFERROR(INDEX(Combination!$N$2:$N$2628,$N8),"") -> 1490 | J8: =IFERROR(INDEX(Combination!$P$2:$P$2628,$N8),"") -> 1490 | M8: =IFERROR(SMALL(Combination!$Q$2:$Q$2628,$A8),"") -> 1490 | N8: =IFERROR(MATCH($M8,Combination!$Q$2:$Q$2628,0),"") -> 319
A9: 2 | B9: =IFERROR(INDEX(Combination!$C$2:$C$2628,$N9),"") -> S.A | C9: =IFERROR(INDEX(Combination!$F$2:$F$2628,$N9),"") -> ICD Dhannad | D9: =IFERROR(INDEX(Combination!$G$2:$G$2628,$N9),"") -> Buenaventura | E9: =IFERROR(INDEX(Combination!$H$2:$H$2628,$N9),"") -> Clearship | F9: =IFERROR(INDEX(Combination!$J$2:$J$2628,$N9),"") -> CMA | G9: =IFERROR(INDEX(Combination!$I$2:$I$2628,$N9),"") -> CIF | H9: =IFERROR(INDEX(Combination!$O$2:$O$2628,$N9),"") -> 0 | I9: =IFERROR(INDEX(Combination!$N$2:$N$2628,$N9),"") -> 1490 | J9: =IFERROR(INDEX(Combination!$P$2:$P$2628,$N9),"") -> 1490 | M9: =IFERROR(SMALL(Combination!$Q$2:$Q$2628,$A9),"") -> 1490 | N9: =IFERROR(MATCH($M9,Combination!$Q$2:$Q$2628,0),"") -> 320
A10: 3 | B10: =IFERROR(INDEX(Combination!$C$2:$C$2628,$N10),"") -> S.A | C10: =IFERROR(INDEX(Combination!$F$2:$F$2628,$N10),"") -> ICD Dhannad | D10: =IFERROR(INDEX(Combination!$G$2:$G$2628,$N10),"") -> Buenaventura | E10: =IFERROR(INDEX(Combination!$H$2:$H$2628,$N10),"") -> Sanjay Forwarder | F10: =IFERROR(INDEX(Combination!$J$2:$J$2628,$N10),"") -> Maersk | G10: =IFERROR(INDEX(Combination!$I$2:$I$2628,$N10),"") -> CIF | H10: =IFERROR(INDEX(Combination!$O$2:$O$2628,$N10),"") -> 0 | I10: =IFERROR(INDEX(Combination!$N$2:$N$2628,$N10),"") -> 2450 | J10: =IFERROR(INDEX(Combination!$P$2:$P$2628,$N10),"") -> 2450 | M10: =IFERROR(SMALL(Combination!$Q$2:$Q$2628,$A10),"") -> 2450 | N10: =IFERROR(MATCH($M10,Combination!$Q$2:$Q$2628,0),"") -> 57
A11: 4 | B11: =IFERROR(INDEX(Combination!$C$2:$C$2628,$N11),"") -> S.A | C11: =IFERROR(INDEX(Combination!$F$2:$F$2628,$N11),"") -> ICD Dhannad | D11: =IFERROR(INDEX(Combination!$G$2:$G$2628,$N11),"") -> Buenaventura | E11: =IFERROR(INDEX(Combination!$H$2:$H$2628,$N11),"") -> Sanjay Forwarder | F11: =IFERROR(INDEX(Combination!$J$2:$J$2628,$N11),"") -> Maersk | G11: =IFERROR(INDEX(Combination!$I$2:$I$2628,$N11),"") -> CIF | H11: =IFERROR(INDEX(Combination!$O$2:$O$2628,$N11),"") -> 0 | I11: =IFERROR(INDEX(Combination!$N$2:$N$2628,$N11),"") -> 2550 | J11: =IFERROR(INDEX(Combination!$P$2:$P$2628,$N11),"") -> 2550 | M11: =IFERROR(SMALL(Combination!$Q$2:$Q$2628,$A11),"") -> 2550 | N11: =IFERROR(MATCH($M11,Combination!$Q$2:$Q$2628,0),"") -> 195
A12: 5 | B12: =IFERROR(INDEX(Combination!$C$2:$C$2628,$N12),"") -> S.A | C12: =IFERROR(INDEX(Combination!$F$2:$F$2628,$N12),"") -> Nhava Sheva | D12: =IFERROR(INDEX(Combination!$G$2:$G$2628,$N12),"") -> Buenaventura | E12: =IFERROR(INDEX(Combination!$H$2:$H$2628,$N12),"") -> Clearship | F12: =IFERROR(INDEX(Combination!$J$2:$J$2628,$N12),"") -> Maersk | G12: =IFERROR(INDEX(Combination!$I$2:$I$2628,$N12),"") -> CIF | H12: =IFERROR(INDEX(Combination!$O$2:$O$2628,$N12),"") -> 1148.5889 | I12: =IFERROR(INDEX(Combination!$N$2:$N$2628,$N12),"") -> 1550 | J12: =IFERROR(INDEX(Combination!$P$2:$P$2628,$N12),"") -> 2698.5889 | M12: =IFERROR(SMALL(Combination!$Q$2:$Q$2628,$A12),"") -> 2698.5889 | N12: =IFERROR(MATCH($M12,Combination!$Q$2:$Q$2628,0),"") -> 397
A13: 6 | B13: =IFERROR(INDEX(Combination!$C$2:$C$2628,$N13),"") -> S.A | C13: =IFERROR(INDEX(Combination!$F$2:$F$2628,$N13),"") -> Nhava Sheva | D13: =IFERROR(INDEX(Combination!$G$2:$G$2628,$N13),"") -> Buenaventura | E13: =IFERROR(INDEX(Combination!$H$2:$H$2628,$N13),"") -> Clearship | F13: =IFERROR(INDEX(Combination!$J$2:$J$2628,$N13),"") -> Maersk | G13: =IFERROR(INDEX(Combination!$I$2:$I$2628,$N13),"") -> CIF | H13: =IFERROR(INDEX(Combination!$O$2:$O$2628,$N13),"") -> 1148.5889 | I13: =IFERROR(INDEX(Combination!$N$2:$N$2628,$N13),"") -> 1550 | J13: =IFERROR(INDEX(Combination!$P$2:$P$2628,$N13),"") -> 2698.5889 | M13: =IFERROR(SMALL(Combination!$Q$2:$Q$2628,$A13),"") -> 2698.5889 | N13: =IFERROR(MATCH($M13,Combination!$Q$2:$Q$2628,0),"") -> 398
A14: 7 | B14: =IFERROR(INDEX(Combination!$C$2:$C$2628,$N14),"") -> S.A | C14: =IFERROR(INDEX(Combination!$F$2:$F$2628,$N14),"") -> Nhava Sheva | D14: =IFERROR(INDEX(Combination!$G$2:$G$2628,$N14),"") -> Buenaventura | E14: =IFERROR(INDEX(Combination!$H$2:$H$2628,$N14),"") -> Sanjay Forwarder | F14: =IFERROR(INDEX(Combination!$J$2:$J$2628,$N14),"") -> Maersk | G14: =IFERROR(INDEX(Combination!$I$2:$I$2628,$N14),"") -> CIF | H14: =IFERROR(INDEX(Combination!$O$2:$O$2628,$N14),"") -> 1148.5889 | I14: =IFERROR(INDEX(Combination!$N$2:$N$2628,$N14),"") -> 1885 | J14: =IFERROR(INDEX(Combination!$P$2:$P$2628,$N14),"") -> 3033.5889 | M14: =IFERROR(SMALL(Combination!$Q$2:$Q$2628,$A14),"") -> 3033.5889 | N14: =IFERROR(MATCH($M14,Combination!$Q$2:$Q$2628,0),"") -> 232
A15: 8 | B15: =IFERROR(INDEX(Combination!$C$2:$C$2628,$N15),"") -> S.A | C15: =IFERROR(INDEX(Combination!$F$2:$F$2628,$N15),"") -> Nhava Sheva | D15: =IFERROR(INDEX(Combination!$G$2:$G$2628,$N15),"") -> Buenaventura | E15: =IFERROR(INDEX(Combination!$H$2:$H$2628,$N15),"") -> Sanjay Forwarder | F15: =IFERROR(INDEX(Combination!$J$2:$J$2628,$N15),"") -> Maersk | G15: =IFERROR(INDEX(Combination!$I$2:$I$2628,$N15),"") -> CIF | H15: =IFERROR(INDEX(Combination!$O$2:$O$2628,$N15),"") -> 1148.5889 | I15: =IFERROR(INDEX(Combination!$N$2:$N$2628,$N15),"") -> 1885 | J15: =IFERROR(INDEX(Combination!$P$2:$P$2628,$N15),"") -> 3033.5889 | M15: =IFERROR(SMALL(Combination!$Q$2:$Q$2628,$A15),"") -> 3033.5889 | N15: =IFERROR(MATCH($M15,Combination!$Q$2:$Q$2628,0),"") -> 233
A16: 9 | B16: =IFERROR(INDEX(Combination!$C$2:$C$2628,$N16),"") -> S.A | C16: =IFERROR(INDEX(Combination!$F$2:$F$2628,$N16),"") -> Nhava Sheva | D16: =IFERROR(INDEX(Combination!$G$2:$G$2628,$N16),"") -> Buenaventura | E16: =IFERROR(INDEX(Combination!$H$2:$H$2628,$N16),"") -> Sanjay Forwarder | F16: =IFERROR(INDEX(Combination!$J$2:$J$2628,$N16),"") -> Maersk | G16: =IFERROR(INDEX(Combination!$I$2:$I$2628,$N16),"") -> CIF | H16: =IFERROR(INDEX(Combination!$O$2:$O$2628,$N16),"") -> 1148.5889 | I16: =IFERROR(INDEX(Combination!$N$2:$N$2628,$N16),"") -> 1935 | J16: =IFERROR(INDEX(Combination!$P$2:$P$2628,$N16),"") -> 3083.5889 | M16: =IFERROR(SMALL(Combination!$Q$2:$Q$2628,$A16),"") -> 3083.5889 | N16: =IFERROR(MATCH($M16,Combination!$Q$2:$Q$2628,0),"") -> 264
A17: 10 | B17: =IFERROR(INDEX(Combination!$C$2:$C$2628,$N17),"") -> S.A | C17: =IFERROR(INDEX(Combination!$F$2:$F$2628,$N17),"") -> Nhava Sheva | D17: =IFERROR(INDEX(Combination!$G$2:$G$2628,$N17),"") -> Buenaventura | E17: =IFERROR(INDEX(Combination!$H$2:$H$2628,$N17),"") -> Sanjay Forwarder | F17: =IFERROR(INDEX(Combination!$J$2:$J$2628,$N17),"") -> Maersk | G17: =IFERROR(INDEX(Combination!$I$2:$I$2628,$N17),"") -> CIF | H17: =IFERROR(INDEX(Combination!$O$2:$O$2628,$N17),"") -> 1148.5889 | I17: =IFERROR(INDEX(Combination!$N$2:$N$2628,$N17),"") -> 1935 | J17: =IFERROR(INDEX(Combination!$P$2:$P$2628,$N17),"") -> 3083.5889 | M17: =IFERROR(SMALL(Combination!$Q$2:$Q$2628,$A17),"") -> 3083.5889 | N17: =IFERROR(MATCH($M17,Combination!$Q$2:$Q$2628,0),"") -> 265
A20: Top 10 Highest Cost Combinations
A21: Rank | B21: Region / Geography | C21: POL | D21: POD | E21: Forwarder | F21: Carrier / Line | G21: Incoterm | H21: Origin Cost (USD) | I21: Ocean Freight (USD) | J21: Total Freight (USD)
A22: 1 | B22: =IFERROR(INDEX(Combination!$C$2:$C$2628,$S22),"") -> S.A | C22: =IFERROR(INDEX(Combination!$F$2:$F$2628,$S22),"") -> Nhava Sheva | D22: =IFERROR(INDEX(Combination!$G$2:$G$2628,$S22),"") -> Buenaventura | E22: =IFERROR(INDEX(Combination!$H$2:$H$2628,$S22),"") -> Sanjay Forwarder | F22: =IFERROR(INDEX(Combination!$J$2:$J$2628,$S22),"") -> Maersk | G22: =IFERROR(INDEX(Combination!$I$2:$I$2628,$S22),"") -> CIF | H22: =IFERROR(INDEX(Combination!$O$2:$O$2628,$S22),"") -> 1148.5889 | I22: =IFERROR(INDEX(Combination!$N$2:$N$2628,$S22),"") -> 2450 | J22: =IFERROR(INDEX(Combination!$P$2:$P$2628,$S22),"") -> 3598.5889 | R22: =IFERROR(LARGE(Combination!$Q$2:$Q$2628,$A22),"") -> 3598.5889 | S22: =IFERROR(MATCH($R22,Combination!$Q$2:$Q$2628,0),"") -> 64
A23: 2 | B23: =IFERROR(INDEX(Combination!$C$2:$C$2628,$S23),"") -> S.A | C23: =IFERROR(INDEX(Combination!$F$2:$F$2628,$S23),"") -> Nhava Sheva | D23: =IFERROR(INDEX(Combination!$G$2:$G$2628,$S23),"") -> Buenaventura | E23: =IFERROR(INDEX(Combination!$H$2:$H$2628,$S23),"") -> Sanjay Forwarder | F23: =IFERROR(INDEX(Combination!$J$2:$J$2628,$S23),"") -> Maersk | G23: =IFERROR(INDEX(Combination!$I$2:$I$2628,$S23),"") -> CIF | H23: =IFERROR(INDEX(Combination!$O$2:$O$2628,$S23),"") -> 1148.5889 | I23: =IFERROR(INDEX(Combination!$N$2:$N$2628,$S23),"") -> 1935 | J23: =IFERROR(INDEX(Combination!$P$2:$P$2628,$S23),"") -> 3083.5889 | R23: =IFERROR(LARGE(Combination!$Q$2:$Q$2628,$A23),"") -> 3083.5889 | S23: =IFERROR(MATCH($R23,Combination!$Q$2:$Q$2628,0),"") -> 265
A24: 3 | B24: =IFERROR(INDEX(Combination!$C$2:$C$2628,$S24),"") -> S.A | C24: =IFERROR(INDEX(Combination!$F$2:$F$2628,$S24),"") -> Nhava Sheva | D24: =IFERROR(INDEX(Combination!$G$2:$G$2628,$S24),"") -> Buenaventura | E24: =IFERROR(INDEX(Combination!$H$2:$H$2628,$S24),"") -> Sanjay Forwarder | F24: =IFERROR(INDEX(Combination!$J$2:$J$2628,$S24),"") -> Maersk | G24: =IFERROR(INDEX(Combination!$I$2:$I$2628,$S24),"") -> CIF | H24: =IFERROR(INDEX(Combination!$O$2:$O$2628,$S24),"") -> 1148.5889 | I24: =IFERROR(INDEX(Combination!$N$2:$N$2628,$S24),"") -> 1935 | J24: =IFERROR(INDEX(Combination!$P$2:$P$2628,$S24),"") -> 3083.5889 | R24: =IFERROR(LARGE(Combination!$Q$2:$Q$2628,$A24),"") -> 3083.5889 | S24: =IFERROR(MATCH($R24,Combination!$Q$2:$Q$2628,0),"") -> 264
A25: 4 | B25: =IFERROR(INDEX(Combination!$C$2:$C$2628,$S25),"") -> S.A | C25: =IFERROR(INDEX(Combination!$F$2:$F$2628,$S25),"") -> Nhava Sheva | D25: =IFERROR(INDEX(Combination!$G$2:$G$2628,$S25),"") -> Buenaventura | E25: =IFERROR(INDEX(Combination!$H$2:$H$2628,$S25),"") -> Sanjay Forwarder | F25: =IFERROR(INDEX(Combination!$J$2:$J$2628,$S25),"") -> Maersk | G25: =IFERROR(INDEX(Combination!$I$2:$I$2628,$S25),"") -> CIF | H25: =IFERROR(INDEX(Combination!$O$2:$O$2628,$S25),"") -> 1148.5889 | I25: =IFERROR(INDEX(Combination!$N$2:$N$2628,$S25),"") -> 1885 | J25: =IFERROR(INDEX(Combination!$P$2:$P$2628,$S25),"") -> 3033.5889 | R25: =IFERROR(LARGE(Combination!$Q$2:$Q$2628,$A25),"") -> 3033.5889 | S25: =IFERROR(MATCH($R25,Combination!$Q$2:$Q$2628,0),"") -> 233
A26: 5 | B26: =IFERROR(INDEX(Combination!$C$2:$C$2628,$S26),"") -> S.A | C26: =IFERROR(INDEX(Combination!$F$2:$F$2628,$S26),"") -> Nhava Sheva | D26: =IFERROR(INDEX(Combination!$G$2:$G$2628,$S26),"") -> Buenaventura | E26: =IFERROR(INDEX(Combination!$H$2:$H$2628,$S26),"") -> Sanjay Forwarder | F26: =IFERROR(INDEX(Combination!$J$2:$J$2628,$S26),"") -> Maersk | G26: =IFERROR(INDEX(Combination!$I$2:$I$2628,$S26),"") -> CIF | H26: =IFERROR(INDEX(Combination!$O$2:$O$2628,$S26),"") -> 1148.5889 | I26: =IFERROR(INDEX(Combination!$N$2:$N$2628,$S26),"") -> 1885 | J26: =IFERROR(INDEX(Combination!$P$2:$P$2628,$S26),"") -> 3033.5889 | R26: =IFERROR(LARGE(Combination!$Q$2:$Q$2628,$A26),"") -> 3033.5889 | S26: =IFERROR(MATCH($R26,Combination!$Q$2:$Q$2628,0),"") -> 232
A27: 6 | B27: =IFERROR(INDEX(Combination!$C$2:$C$2628,$S27),"") -> S.A | C27: =IFERROR(INDEX(Combination!$F$2:$F$2628,$S27),"") -> Nhava Sheva | D27: =IFERROR(INDEX(Combination!$G$2:$G$2628,$S27),"") -> Buenaventura | E27: =IFERROR(INDEX(Combination!$H$2:$H$2628,$S27),"") -> Clearship | F27: =IFERROR(INDEX(Combination!$J$2:$J$2628,$S27),"") -> Maersk | G27: =IFERROR(INDEX(Combination!$I$2:$I$2628,$S27),"") -> CIF | H27: =IFERROR(INDEX(Combination!$O$2:$O$2628,$S27),"") -> 1148.5889 | I27: =IFERROR(INDEX(Combination!$N$2:$N$2628,$S27),"") -> 1550 | J27: =IFERROR(INDEX(Combination!$P$2:$P$2628,$S27),"") -> 2698.5889 | R27: =IFERROR(LARGE(Combination!$Q$2:$Q$2628,$A27),"") -> 2698.5889 | S27: =IFERROR(MATCH($R27,Combination!$Q$2:$Q$2628,0),"") -> 398
A28: 7 | B28: =IFERROR(INDEX(Combination!$C$2:$C$2628,$S28),"") -> S.A | C28: =IFERROR(INDEX(Combination!$F$2:$F$2628,$S28),"") -> Nhava Sheva | D28: =IFERROR(INDEX(Combination!$G$2:$G$2628,$S28),"") -> Buenaventura | E28: =IFERROR(INDEX(Combination!$H$2:$H$2628,$S28),"") -> Clearship | F28: =IFERROR(INDEX(Combination!$J$2:$J$2628,$S28),"") -> Maersk | G28: =IFERROR(INDEX(Combination!$I$2:$I$2628,$S28),"") -> CIF | H28: =IFERROR(INDEX(Combination!$O$2:$O$2628,$S28),"") -> 1148.5889 | I28: =IFERROR(INDEX(Combination!$N$2:$N$2628,$S28),"") -> 1550 | J28: =IFERROR(INDEX(Combination!$P$2:$P$2628,$S28),"") -> 2698.5889 | R28: =IFERROR(LARGE(Combination!$Q$2:$Q$2628,$A28),"") -> 2698.5889 | S28: =IFERROR(MATCH($R28,Combination!$Q$2:$Q$2628,0),"") -> 397
A29: 8 | B29: =IFERROR(INDEX(Combination!$C$2:$C$2628,$S29),"") -> S.A | C29: =IFERROR(INDEX(Combination!$F$2:$F$2628,$S29),"") -> ICD Dhannad | D29: =IFERROR(INDEX(Combination!$G$2:$G$2628,$S29),"") -> Buenaventura | E29: =IFERROR(INDEX(Combination!$H$2:$H$2628,$S29),"") -> Sanjay Forwarder | F29: =IFERROR(INDEX(Combination!$J$2:$J$2628,$S29),"") -> Maersk | G29: =IFERROR(INDEX(Combination!$I$2:$I$2628,$S29),"") -> CIF | H29: =IFERROR(INDEX(Combination!$O$2:$O$2628,$S29),"") -> 0 | I29: =IFERROR(INDEX(Combination!$N$2:$N$2628,$S29),"") -> 2550 | J29: =IFERROR(INDEX(Combination!$P$2:$P$2628,$S29),"") -> 2550 | R29: =IFERROR(LARGE(Combination!$Q$2:$Q$2628,$A29),"") -> 2550 | S29: =IFERROR(MATCH($R29,Combination!$Q$2:$Q$2628,0),"") -> 195
A30: 9 | B30: =IFERROR(INDEX(Combination!$C$2:$C$2628,$S30),"") -> S.A | C30: =IFERROR(INDEX(Combination!$F$2:$F$2628,$S30),"") -> ICD Dhannad | D30: =IFERROR(INDEX(Combination!$G$2:$G$2628,$S30),"") -> Buenaventura | E30: =IFERROR(INDEX(Combination!$H$2:$H$2628,$S30),"") -> Sanjay Forwarder | F30: =IFERROR(INDEX(Combination!$J$2:$J$2628,$S30),"") -> Maersk | G30: =IFERROR(INDEX(Combination!$I$2:$I$2628,$S30),"") -> CIF | H30: =IFERROR(INDEX(Combination!$O$2:$O$2628,$S30),"") -> 0 | I30: =IFERROR(INDEX(Combination!$N$2:$N$2628,$S30),"") -> 2450 | J30: =IFERROR(INDEX(Combination!$P$2:$P$2628,$S30),"") -> 2450 | R30: =IFERROR(LARGE(Combination!$Q$2:$Q$2628,$A30),"") -> 2450 | S30: =IFERROR(MATCH($R30,Combination!$Q$2:$Q$2628,0),"") -> 57
A31: 10 | B31: =IFERROR(INDEX(Combination!$C$2:$C$2628,$S31),"") -> S.A | C31: =IFERROR(INDEX(Combination!$F$2:$F$2628,$S31),"") -> ICD Dhannad | D31: =IFERROR(INDEX(Combination!$G$2:$G$2628,$S31),"") -> Buenaventura | E31: =IFERROR(INDEX(Combination!$H$2:$H$2628,$S31),"") -> Clearship | F31: =IFERROR(INDEX(Combination!$J$2:$J$2628,$S31),"") -> CMA | G31: =IFERROR(INDEX(Combination!$I$2:$I$2628,$S31),"") -> CIF | H31: =IFERROR(INDEX(Combination!$O$2:$O$2628,$S31),"") -> 0 | I31: =IFERROR(INDEX(Combination!$N$2:$N$2628,$S31),"") -> 1490 | J31: =IFERROR(INDEX(Combination!$P$2:$P$2628,$S31),"") -> 1490 | R31: =IFERROR(LARGE(Combination!$Q$2:$Q$2628,$A31),"") -> 1490 | S31: =IFERROR(MATCH($R31,Combination!$Q$2:$Q$2628,0),"") -> 320

Sheet Origin Costs
A1: Exchange Rate (INR per USD) | B1: 90
A3: POL: Nhava Sheva
A4: Carrier / Line | B4: Origin Cost (INR) | C4: Origin Cost (USD)
A5: 10 Cubits | B5: 0 | C5: =IFERROR(B5/$B$1,0) -> 0
A6: Ageon | B6: 0 | C6: =IFERROR(B6/$B$1,0) -> 0
A7: Akkon | B7: 0 | C7: =IFERROR(B7/$B$1,0) -> 0
A8: ANL | B8: 0 | C8: =IFERROR(B8/$B$1,0) -> 0
A9: Arkas | B9: 0 | C9: =IFERROR(B9/$B$1,0) -> 0
A10: Blue Marlin | B10: 0 | C10: =IFERROR(B10/$B$1,0) -> 0
A11: CMA | B11: 0 | C11: =IFERROR(B11/$B$1,0) -> 0
A12: Corten Shipping | B12: 0 | C12: =IFERROR(B12/$B$1,0) -> 0
A13: Corton | B13: 0 | C13: =IFERROR(B13/$B$1,0) -> 0
A14: Cosco | B14: 0 | C14: =IFERROR(B14/$B$1,0) -> 0
A15: Econship | B15: 0 | C15: =IFERROR(B15/$B$1,0) -> 0
A16: Emirates | B16: 0 | C16: =IFERROR(B16/$B$1,0) -> 0
... A44: YML | B44: 0 | C44: =IFERROR(B44/$B$1,0) -> 0
A47: POL: ICD Tihi
A48: Carrier / Line | B48: Origin Cost (INR) | C48: Origin Cost (USD)
A49: 10 Cubits | B49: 0 | C49: =IFERROR(B49/$B$1,0) -> 0
A50: Ageon | B50: 0 | C50: =IFERROR(B50/$B$1,0) -> 0
A51: Akkon | B51: 0 | C51: =IFERROR(B51/$B$1,0) -> 0
A52: ANL | B52: 0 | C52: =IFERROR(B52/$B$1,0) -> 0
A53: Arkas | B53: 0 | C53: =IFERROR(B53/$B$1,0) -> 0
A54: Blue Marlin | B54: 0 | C54: =IFERROR(B54/$B$1,0) -> 0
A55: CMA | B55: 99987 | C55: =IFERROR(B55/$B$1,0) -> 1110.9667
A56: Corten Shipping | B56: 0 | C56: =IFERROR(B56/$B$1,0) -> 0
A57: Corton | B57: 0 | C57: =IFERROR(B57/$B$1,0) -> 0
A58: Cosco | B58: 0 | C58: =IFERROR(B58/$B$1,0) -> 0
A59: Econship | B59: 0 | C59: =IFERROR(B59/$B$1,0) -> 0
A60: Emirates | B60: 0 | C60: =IFERROR(B60/$B$1,0) -> 0
... A88: YML | B88: 0 | C88: =IFERROR(B88/$B$1,0) -> 0
A91: POL: ICD Dhannad
A92: Carrier / Line | B92: Origin Cost (INR) | C92: Origin Cost (USD)
A93: 10 Cubits | B93: 0 | C93: =IFERROR(B93/$B$1,0) -> 0
A94: Ageon | B94: 0 | C94: =IFERROR(B94/$B$1,0) -> 0
A95: Akkon | B95: 0 | C95: =IFERROR(B95/$B$1,0) -> 0
A96: ANL | B96: 0 | C96: =IFERROR(B96/$B$1,0) -> 0
A97: Arkas | B97: 0 | C97: =IFERROR(B97/$B$1,0) -> 0
A98: Blue Marlin | B98: 0 | C98: =IFERROR(B98/$B$1,0) -> 0
A99: CMA | B99: 0 | C99: =IFERROR(B99/$B$1,0) -> 0
A100: Corten Shipping | B100: 0 | C100: =IFERROR(B100/$B$1,0) -> 0
A101: Corton | B101: 0 | C101: =IFERROR(B101/$B$1,0) -> 0
A102: Cosco | B102: 0 | C102: =IFERROR(B102/$B$1,0) -> 0
A103: Econship | B103: 0 | C103: =IFERROR(B103/$B$1,0) -> 0
A104: Emirates | B104: 0 | C104: =IFERROR(B104/$B$1,0) -> 0
... A132: YML | B132: 0 | C132: =IFERROR(B132/$B$1,0) -> 0

Sheet Sheet1
A1: Planned loading date | B1: Month | C1: Geography | D1: Container number | E1: Customer | F1: Country | G1: INCO | H1: Forwarder | I1: Pick up date | J1: Port | K1: Line | L1: Transporter | M1: POD | N1: O/F | O1: ROW/RTNA | P1: Invoice Date | Q1: Inovice Month
A2: 45751 | B2: Apr | C2: MEA | D2: TSAU5601222 | E2: Nahar Al Ajnas Auto Spre Prts Tradi, Dubai (In) | F2: DI | G2: FOB | H2: GACIS CARGO | I2: 45750 | J2: NH | K2: InterGlobe Marine | L2: Hariom | M2: Jebel Ali | O2: ROW | P2: 45753 | Q2: Apr-25
A3: 45751 | B3: Apr | C3: MEA | D3: TCLU8434589 | E3: Nahar Al Ajnas Auto Spre Prts Tradi, Dubai (In) | F3: DI | G3: FOB | H3: GACIS CARGO | I3: 45750 | J3: NH | K3: InterGlobe Marine | L3: Hariom | M3: Jebel Ali | O3: ROW | P3: 45753 | Q3: Apr-25
A4: 45752 | B4: Apr | C4: MEA | D4: MEDU8324457 | E4: SHOAIB FAISAL QALANDARI LTD | F4: Afghanistan | G4: FOB | H4: IGM Shipping | I4: 45745 | J4: NH | K4: InterGlobe Marine | L4: Hariom | M4: Jebel Ali | O4: ROW | P4: 45754 | Q4: Apr-25
A5: 45751 | B5: Apr | C5: MEA | D5: TCNU6730450 | E5: Nahar Al Ajnas Auto Spre Prts Tradi, Dubai (In) | F5: DI | G5: FOB | H5: GACIS CARGO | I5: 45750 | J5: NH | K5: InterGlobe Marine | L5: Hariom | M5: Jebel Ali | O5: ROW | P5: 45759 | Q5: Apr-25
A6: 45751 | B6: Apr | C6: MEA | D6: TCLU5315565 | E6: Nahar Al Ajnas Auto Spre Prts Tradi, Dubai (In) | F6: DI | G6: FOB | H6: GACIS CARGO | I6: 45750 | J6: NH | K6: InterGlobe Marine | L6: Hariom | M6: Jebel Ali | O6: ROW | P6: 45759 | Q6: Apr-25
A7: 45751 | B7: Apr | C7: MEA | D7: TCNU6378478 | E7: Nahar Al Ajnas Auto Spre Prts Tradi, Dubai (In) | F7: DI | G7: FOB | H7: GACIS CARGO | I7: 45750 | J7: NH | K7: InterGlobe Marine | L7: Hariom | M7: Jebel Ali | O7: ROW | P7: 45759 | Q7: Apr-25
A8: 45762 | B8: Apr | C8: S.A. | D8: TGHU6354879 | E8: MULTILLANTAS ZONA LIBRE S.A., Panama | F8: Columbia | G8: FOB | H8: Pisces shipping | I8: 45761 | J8: NH | K8: CMA | L8: Hariom | M8: Buenaventura | O8: ROW | P8: 45763 | Q8: Apr-25
A9: 45762 | B9: Apr | C9: S.A. | D9: TCNU3994171 | E9: MULTILLANTAS ZONA LIBRE S.A., Panama | F9: Columbia | G9: FOB | H9: Pisces shipping | I9: 45761 | J9: NH | K9: CMA | L9: Hariom | M9: Buenaventura | O9: ROW | P9: 45766 | Q9: Apr-25
A10: 45769 | B10: Apr | C10: Europe | D10: BSIU9068251 | E10: BA Bush Tyres | F10: United Kingdom | G10: FOB | H10: Transbox | I10: 45769 | J10: ICD | K10: Hapag | L10: ICD | M10: London Gateway | N10: 1325 | O10: ROW | P10: 45768 | Q10: Apr-25
A11: 45768 | B11: Apr | C11: S.A. | D11: EITU9087875 | E11: MULTILLANTAS ZONA LIBRE S.A., Panama | F11: Panama | G11: CIF | H11: Kotak Global | I11: 45766 | J11: NH | K11: Evergreen | L11: RKY | M11: Manzanilo | N11: 3350 | O11: ROW | P11: 45768 | Q11: Apr-25
A12: 45767 | B12: Apr | C12: Europe | D12: TXGU8753293 | E12: TRADELUC FZE LLC, Spain | F12: Spain | G12: FOB | H12: Active Shipping | I12: 45765 | J12: NH | K12: Hyundai | L12: Hariom | M12: Valencia | O12: ROW | P12: 45768 | Q12: Apr-25
A13: 45768 | B13: Apr | C13: MEA | D13: CSYU4030497 | E13: Al Rabee - Sudan | F13: Sudan | G13: CIF | H13: Hind Freight | I13: 45766 | J13: NH | K13: Transmar | L13: Hariom | M13: Sudan Port | N13: 2050 | O13: ROW | P13: 45769 | Q13: Apr-25
A14: 45768 | B14: Apr | C14: MEA | D14: TMCU5006322 | E14: Al Rabee - Sudan | F14: Sudan | G14: CIF | H14: Hind Freight | I14: 45766 | J14: NH | K14: Transmar | L14: Hariom | M14: Sudan Port | N14: 2050 | O14: ROW | P14: 45769 | Q14: Apr-25
A15: 45768 | B15: Apr | C15: MEA | D15: SELU4015437 | E15: Al Rabee - Sudan | F15: Sudan | G15: CIF | H15: Hind Freight | I15: 45766 | J15: NH | K15: Transmar | L15: Hariom | M15: Sudan Port | N15: 2050 | O15: ROW | P15: 45769 | Q15: Apr-25
A16: 45768 | B16: Apr | C16: MEA | D16: ASLU7065451 | E16: Al Rabee - Sudan | F16: Sudan | G16: CIF | H16: Hind Freight | I16: 45766 | J16: NH | K16: Transmar | L16: Hariom | M16: Sudan Port | N16: 2050 | O16: ROW | P16: 45769 | Q16: Apr-25
A17: 45769 | B17: Apr | C17: Europe | D17: FANU1807821 | E17: BA Bush Tyres | F17: United Kingdom | G17: FOB | H17: Transbox | I17: 45769 | J17: ICD | K17: Hapag | L17: ICD | M17: London Gateway | N17: 1325 | O17: ROW | P17: 45769 | Q17: Apr-25
A18: 45769 | B18: Apr | C18: Europe | D18: HAMU1269046 | E18: BA Bush Tyres | F18: United Kingdom | G18: FOB | H18: Transbox | I18: 45769 | J18: ICD | K18: Hapag | L18: ICD | M18: London Gateway | N18: 1325 | O18: ROW | P18: 45769 | Q18: Apr-25
A19: 45769 | B19: Apr | C19: Europe | D19: DFSU6944634 | E19: BA Bush Tyres | F19: United Kingdom | G19: FOB | H19: Transbox | I19: 45772 | J19: ICD | K19: Hapag | L19: ICD | M19: London Gateway | N19: 1325 | O19: ROW | P19: 45770 | Q19: Apr-25
A20: 45771 | B20: Apr | C20: S.A. | D20: MSMU5233491 | E20: CPX DISTRIBUIDORA S/A-Suape | F20: Brazil | G20: FOB | H20: Sanjay Forwarder | I20: 45770 | J20: Tihi | K20: MSC | L20: TRS | M20: Suape | O20: ROW | P20: 45771 | Q20: Apr-25
A21: 45772 | B21: Apr | C21: S.A. | D21: CAAU5584816 | E21: CPX DISTRIBUIDORA S/A-Itajai | F21: Brazil | G21: FOB | H21: Sanjay Forwarder | I21: 45771 | J21: NH | K21: MSC | L21: RKY | M21: Itajai | O21: ROW | P21: 45773 | Q21: Apr-25
A22: 45772 | B22: Apr | C22: S.A. | D22: MSNU5276202 | E22: CPX DISTRIBUIDORA S/A-Itajai | F22: Brazil | G22: FOB | H22: Sanjay Forwarder | I22: 45771 | J22: NH | K22: MSC | L22: RKY | M22: Itajai | O22: ROW | P22: 45773 | Q22: Apr-25
A23: 45772 | B23: Apr | C23: S.A. | D23: MSNU9786122 | E23: CPX DISTRIBUIDORA S/A-Itajai | F23: Brazil | G23: FOB | H23: Sanjay Forwarder | I23: 45771 | J23: NH | K23: MSC | L23: RKY | M23: Itajai | O23: ROW | P23: 45773 | Q23: Apr-25
A24: 45773 | B24: Apr | C24: Europe | D24: HLBU2787369 | E24: Marco Lankes GmbH, Germany | F24: Germany | G24: FOB | H24: Hellmann | I24: 45773 | J24: ICD | K24: Hapag | L24: ICD | M24: ROTTERDAM | N24: 1200 | O24: ROW | P24: 45774 | Q24: Apr-25
A25: 45773 | B25: Apr | C25: Europe | D25: CAAU5327171 | E25: Marco Lankes GmbH, Germany | F25: Germany | G25: FOB | H25: Hellmann | I25: 45773 | J25: ICD | K25: Hapag | L25: ICD | M25: ROTTERDAM | N25: 1200 | O25: ROW | P25: 45774 | Q25: Apr-25
A26: 45773 | B26: Apr | C26: Europe | D26: FANU1628106 | E26: Marco Lankes GmbH, Germany | F26: Germany | G26: FOB | H26: Hellmann | I26: 45773 | J26: ICD | K26: Hapag | L26: ICD | M26: ROTTERDAM | N26: 1200 | O26: ROW | P26: 45774 | Q26: Apr-25
A27: 45774 | B27: Apr | C27: Europe | D27: TLLU4214305 | E27: BA Bush Tyres | F27: United Kingdom | G27: FOB | H27: Transbox | I27: 45774 | J27: ICD | K27: Hapag | L27: ICD | M27: London Gateway | N27: 1325 | O27: ROW | P27: 45775 | Q27: Apr-25
A28: 45774 | B28: Apr | C28: Europe | D28: HAMU1264635 | E28: BA Bush Tyres | F28: United Kingdom | G28: FOB | H28: Transbox | I28: 45774 | J28: ICD | K28: Hapag | L28: ICD | M28: London Gateway | N28: 1325 | O28: ROW | P28: 45775 | Q28: Apr-25
A29: 45775 | B29: Apr | C29: MEA | D29: FSCU8431960 | E29: AL-DYAR AL-KHADRAA TIRE AND BATTERY, Iraq | F29: Iraq | G29: CIF | H29: DP World | I29: 45775 | J29: ICD | K29: Hapag | L29: ICD | M29: Umm Qasr | N29: 950 | O29: ROW | P29: 45776 | Q29: Apr-25
A30: 45775 | B30: Apr | C30: MEA | D30: UACU5593483 | E30: AL-DYAR AL-KHADRAA TIRE AND BATTERY, Iraq | F30: Iraq | G30: CIF | H30: DP World | I30: 45775 | J30: ICD | K30: Hapag | L30: ICD | M30: Umm Qasr | N30: 950 | O30: ROW | P30: 45776 | Q30: Apr-25
A31: 45774 | B31: Apr | C31: Europe | D31: UETU5822331 | E31: Agrigear LTD, Ireland | F31: Germany | G31: CIF | H31: Hellmann | I31: 45775 | J31: ICD | K31: Hapag | L31: ICD | M31: Dublin | N31: 1650 | O31: ROW | P31: 45778 | Q31: Apr-25
A32: 45779 | B32: May | C32: Europe | D32: HASU4672400 | E32: Inter Cars S.A., Poland | F32: Poland | G32: FOB | H32: Clearship | I32: 45777 | J32: NH | K32: Maersk | L32: RKY | M32: Gdansk | O32: ROW | P32: 45781 | Q32: May-25
A33: 45779 | B33: May | C33: Europe | D33: MSKU0447268 | E33: Inter Cars S.A., Poland | F33: Poland | G33: FOB | H33: Clearship | I33: 45777 | J33: NH | K33: Maersk | L33: RKY | M33: Gdansk | O33: ROW | P33: 45781 | Q33: May-25
A34: 45785 | B34: May | C34: ISC | D34: OOLU0242146 | E34: Supergrip International (Pvt) Ltd | F34: Srilanka | G34: FOB | H34: Gonsai Logistcs | I34: 45784 | J34: NH | K34: COSCO | L34: RKY | M34: Colombo | O34: ROW | P34: 45788 | Q34: May-25
A35: 45785 | B35: May | C35: Europe | D35: TGBU8017052 | E35: UAB Inter Cars Lietuva, Lithuania | F35: Lithuania | G35: FOB | H35: Hellmann | I35: 45784 | J35: ICD | K35: MSC | L35: ICD | M35: Klaipeda | O35: ROW | P35: 45788 | Q35: May-25
A36: 45788 | B36: May | C36: MEA | D36: TCNU3311085 | E36: Vaal Tyre Centre Holdings (Pty) Ltd-S.A | F36: South Africa | G36: FOB | H36: Hellmann | I36: 45786 | J36: NH | K36: CMA | L36: Hariom | M36: Durban | N36: 989 | O36: ROW | P36: 45788 | Q36: May-25
A37: 45794 | B37: May | C37: Europe | D37: TGBU5697043 | E37: Intercars, Germany | F37: Germany | G37: DDP | H37: Hellmann | I37: 45792 | J37: NH | K37: Hapag | L37: Hariom | M37: Rotterdam | N37: 1100 | O37: ROW | P37: 45794 | Q37: May-25
A38: 45795 | B38: May | C38: MEA | D38: CAAU9052344 | E38: Al Rabee - Sudan | F38: Sudan | G38: FOB | H38: Arikas Logistics | I38: 45793 | J38: NH | K38: PIL | L38: Hariom | M38: Port Sudan | O38: ROW | P38: 45795 | Q38: May-25
A39: 45795 | B39: May | C39: MEA | D39: PCIU9384484 | E39: Al Rabee - Sudan | F39: Sudan | G39: FOB | H39: Arikas Logistics | I39: 45793 | J39: NH | K39: PIL | L39: Hariom | M39: Port Sudan | O39: ROW | P39: 45795 | Q39: May-25
A40: 45795 | B40: May | C40: MEA | D40: PCIU9286425 | E40: Al Rabee - Sudan | F40: Sudan | G40: FOB | H40: Arikas Logistics | I40: 45793 | J40: NH | K40: PIL | L40: Hariom | M40: Port Sudan | O40: ROW | P40: 45795 | Q40: May-25
A41: 45795 | B41: May | C41: MEA | D41: GAOU7195672 | E41: Al Rabee - Sudan | F41: Sudan | G41: FOB | H41: Arikas Logistics | I41: 45793 | J41: NH | K41: PIL | L41: Hariom | M41: Port Sudan | O41: ROW | P41: 45795 | Q41: May-25
A42: 45795 | B42: May | C42: MEA | D42: PIDU4042584 | E42: Al Rabee - Sudan | F42: Sudan | G42: FOB | H42: Arikas Logistics | I42: 45793 | J42: NH | K42: PIL | L42: Hariom | M42: Port Sudan | O42: ROW | P42: 45795 | Q42: May-25
A43: 45795 | B43: May | C43: MEA | D43: PCIU9331627 | E43: Al Rabee - Sudan | F43: Sudan | G43: FOB | H43: Arikas Logistics | I43: 45793 | J43: NH | K43: PIL | L43: Hariom | M43: Port Sudan | O43: ROW | P43: 45795 | Q43: May-25
A44: 45794 | B44: May | C44: Europe | D44: BMOU5257354 | E44: BA Bush Tyres | F44: United Kingdom | G44: CIF | H44: Kotak Global | I44: 45794 | J44: ICD | K44: Hapag | L44: ICD | M44: London Gateway | N44: 1050 | O44: ROW | P44: 45795 | Q44: May-25
A45: 45795 | B45: May | C45: MEA | D45: FBLU0146615 | E45: Al Rabee - Sudan | F45: Sudan | G45: FOB | H45: Arikas Logistics | I45: 45793 | J45: NH | K45: PIL | L45: Hariom | M45: Port Sudan | O45: ROW | P45: 45797 | Q45: May-25
A46: 45803 | B46: May | C46: Europe | D46: HAMU3446541 | E46: BA Bush Tyres | F46: United Kingdom | G46: CIF | H46: Kotak Global | I46: 45803 | J46: Tihi | K46: Hapag | L46: TRS | M46: London Gateway | N46: 1050 | O46: ROW | P46: 45804 | Q46: May-25
A47: 45803 | B47: May | C47: Europe | D47: HAMU2772121 | E47: BA Bush Tyres | F47: United Kingdom | G47: CIF | H47: Kotak Global | I47: 45805 | J47: Tihi | K47: Hapag | L47: TRS | M47: London Gateway | N47: 1050 | O47: ROW | P47: 45804 | Q47: May-25
A48: 45805 | B48: May | C48: Europe | D48: HAMU2319244 | E48: BA Bush Tyres | F48: United Kingdom | G48: CIF | H48: Kotak Global | I48: 45805 | J48: NH | K48: Hapag | L48: RKY | M48: London Gateway | N48: 1050 | O48: ROW | P48: 45805 | Q48: May-25
A49: 45805 | B49: May | C49: Europe | D49: HLBU2146724 | E49: BA Bush Tyres | F49: United Kingdom | G49: CIF | H49: Kotak Global | I49: 45805 | J49: NH | K49: Hapag | L49: RKY | M49: London Gateway | N49: 1050 | O49: ROW | P49: 45805 | Q49: May-25
A50: 45805 | B50: May | C50: Europe | D50: MTSU9656005 | E50: BA Bush Tyres | F50: United Kingdom | G50: CIF | H50: Kotak Global | I50: 45803 | J50: NH | K50: Hapag | L50: RKY | M50: London Gateway | N50: 1050 | O50: ROW | P50: 45806 | Q50: May-25
A51: 45807 | B51: May | C51: Europe | D51: TCLU7907244 | E51: Inter Cars S.A., Poland | F51: Poland | G51: FOB | H51: Rohlig India | I51: 45805 | J51: NH | K51: ONE | L51: Hariom | M51: Gdynia | O51: ROW | P51: 45807 | Q51: May-25
A52: 45808 | B52: May | C52: Europe | D52: APHU7384286 | E52: Inter Cars Bulgaria EOOD | F52: Bulgaria | G52: FOB | H52: Fortune Inc | I52: 45806 | J52: NH | K52: CMA | L52: Hariom | M52: Thessaloniki | O52: ROW | P52: 45808 | Q52: May-25
A53: 45807 | B53: May | C53: Europe | D53: KKFU7527584 | E53: Inter Cars S.A., Poland | F53: Poland | G53: FOB | H53: Rohlig India | I53: 45805 | J53: NH | K53: ONE | L53: Hariom | M53: Gdynia | O53: ROW | P53: 45808 | Q53: May-25
A54: 45806 | B54: May | C54: MEA | D54: TGHU8587479 | E54: Nahar Al Ajnas Auto Spre Prts Tradi, Dubai (In) | F54: DI | G54: FOB | H54: GACIS Cargo | I54: 45804 | J54: NH | K54: X TRANS | L54: RKY | M54: Jebel Ali | O54: ROW | P54: 45808 | Q54: May-25
A55: 45806 | B55: May | C55: MEA | D55: CINU6316866 | E55: Nahar Al Ajnas Auto Spre Prts Tradi, Dubai (In) | F55: DI | G55: FOB | H55: GACIS Cargo | I55: 45804 | J55: NH | K55: X TRANS | L55: RKY | M55: Jebel Ali | O55: ROW | P55: 45808 | Q55: May-25
A56: 45806 | B56: May | C56: MEA | D56: APHU6331300 | E56: Nahar Al Ajnas Auto Spre Prts Tradi, Dubai (In) | F56: DI | G56: FOB | H56: GACIS Cargo | I56: 45804 | J56: NH | K56: X TRANS | L56: RKY | M56: Jebel Ali | O56: ROW | P56: 45808 | Q56: May-25
A57: 45806 | B57: May | C57: MEA | D57: APHU6349608 | E57: Nahar Al Ajnas Auto Spre Prts Tradi, Dubai (In) | F57: DI | G57: FOB | H57: GACIS Cargo | I57: 45804 | J57: NH | K57: X TRANS | L57: RKY | M57: Jebel Ali | O57: ROW | P57: 45808 | Q57: May-25
A58: 45818 | B58: Jun | C58: S.A | D58: TCKU6867480 | E58: Acostallantas S.A, Colombia | F58: columbia | G58: CIF | H58: Sanjay Forwarder | I58: 45817 | J58: ICD | K58: Maersk | L58: Pegasus | M58: Buenaventura | N58: 2450 | O58: ROW | P58: 45818 | Q58: Jun-25
A59: 45818 | B59: Jun | C59: S.A | D59: CMAU3843908 | E59: REDLLANTAS S.A | F59: columbia | G59: FOB | H59: Mentor Freight | I59: 45815 | J59: ICD | K59: CMA | L59: Pegasus | M59: Buenaventura | O59: ROW | P59: 45818 | Q59: Jun-25
A60: 45819 | B60: Jun | C60: ISC | D60: HAMU1010081 | E60: Nonime Enterprises, Srilanka | F60: Srilanka | G60: FOB | H60: Everprime | I60: 45817 | J60: NH | K60: MSA Shipping | L60: RKY | M60: Colombo | O60: ROW | P60: 45819 | Q60: Jun-25
A61: 45819 | B61: Jun | C61: Europe | D61: HLBU1602178 | E61: Tuncay Güç Mansa Kallpa External, Turkey | F61: Turkey | G61: CIF | H61: Hellmann | I61: 45818 | J61: ICD | K61: Hapag | L61: Pegasus | M61: Aliaga | N61: 1235 | O61: ROW | P61: 45819 | Q61: Jun-25
A62: 45819 | B62: Jun | C62: Europe | D62: CRSU9030738 | E62: Inter Cars d.o.o., Croatia | F62: Croatia | G62: FOB | H62: Cargo Partner | I62: 45819 | J62: ICD | K62: MSC | L62: Pegasus | M62: Rijeka | N62: FOB | O62: ROW | P62: 45820 | Q62: Jun-25
A63: 45819 | B63: Jun | C63: Europe | D63: MEDU7884971 | E63: Inter Cars Romania Srl | F63: Romania | G63: FOB | H63: DSV | I63: 45819 | J63: ICD | K63: MSC | L63: Pegasus | M63: Constanta | N63: FOB | O63: ROW | P63: 45820 | Q63: Jun-25
A64: 45822 | B64: Jun | C64: Europe | D64: BEAU6096136 | E64: Inter Cars Greece Ltd | F64: Greece | G64: FOB | H64: Team Global | I64: 45820 | J64: NH | K64: CMA | L64: RKY | M64: PIRAEUS | N64: FOB | O64: ROW | P64: 45822 | Q64: Jun-25
A65: 45824 | B65: Jun | C65: S.A | D65: MRKU4988090 | E65: Acostallantas S.A, Colombia | F65: columbia | G65: CIF | H65: Sanjay Forwarder | J65: NH | K65: Maersk | L65: Hariom | M65: Buenaventura | N65: 2450 | O65: ROW | P65: 45824 | Q65: Jun-25
A66: 45824 | B66: Jun | C66: MEA | D66: MRKU5907620 | E66: ROAD FORCE AUTO SPARE PARTS-Sharjah | F66: UAE | G66: FOB | H66: Arikas Logistics | I66: 45822 | J66: NH | K66: Maersk | L66: Hariom | M66: Sharjah | O66: ROW | P66: 45825 | Q66: Jun-25
A67: 45824 | B67: Jun | C67: MEA | D67: MRSU5643773 | E67: ROAD FORCE AUTO SPARE PARTS-Sharjah | F67: UAE | G67: FOB | H67: Arikas Logistics | I67: 45822 | J67: NH | K67: Maersk | L67: Hariom | M67: Sharjah | O67: ROW | P67: 45825 | Q67: Jun-25
A68: 45824 | B68: Jun | C68: MEA | D68: HASU4409375 | E68: ROAD FORCE AUTO SPARE PARTS-Sharjah | F68: UAE | G68: FOB | H68: Arikas Logistics | I68: 45822 | J68: NH | K68: Maersk | L68: Hariom | M68: Sharjah | O68: ROW | P68: 45825 | Q68: Jun-25
A69: 45826 | B69: Jun | C69: Europe | D69: ONEU0526521 | E69: Inter Cars S.A., Poland | F69: Poland | G69: FOB | H69: VR Logistics | I69: 45824 | J69: NH | K69: ONE | L69: Hariom | M69: Gdynia | N69: FOB | O69: ROW | P69: 45826 | Q69: Jun-25
A70: 45824 | B70: Jun | C70: MEA | D70: HASU4496934 | E70: ROAD FORCE AUTO SPARE PARTS-Sharjah | F70: UAE | G70: FOB | H70: Arikas Logistics | I70: 45822 | J70: NH | K70: Maersk | L70: Hariom | M70: Sharjah | O70: ROW | P70: 45826 | Q70: Jun-25
A71: 45824 | B71: Jun | C71: MEA | D71: MSKU9506443 | E71: ROAD FORCE AUTO SPARE PARTS-Sharjah | F71: UAE | G71: FOB | H71: Arikas Logistics | I71: 45822 | J71: NH | K71: Maersk | L71: Hariom | M71: Sharjah | O71: ROW | P71: 45826 | Q71: Jun-25
A72: 45824 | B72: Jun | C72: MEA | D72: MSKU1182760 | E72: ROAD FORCE AUTO SPARE PARTS-Sharjah | F72: UAE | G72: FOB | H72: Arikas Logistics | I72: 45822 | J72: NH | K72: Maersk | L72: Hariom | M72: Sharjah | O72: ROW | P72: 45826 | Q72: Jun-25
A73: 45826 | B73: Jun | C73: Europe | D73: ONEU5599074 | E73: Inter Cars S.A., Poland | F73: Poland | G73: FOB | H73: VR Logistics | I73: 45824 | J73: NH | K73: ONE | L73: Hariom | M73: Gdynia | N73: FOB | O73: ROW | P73: 45827 | Q73: Jun-25
A74: 45826 | B74: Jun | C74: Europe | D74: ONEU5357609 | E74: Inter Cars S.A., Poland | F74: Poland | G74: FOB | H74: VR Logistics | I74: 45824 | J74: NH | K74: ONE | L74: Hariom | M74: Gdynia | N74: FOB | O74: ROW | P74: 45828 | Q74: Jun-25
A75: 45826 | B75: Jun | C75: Europe | D75: ONEU5123848 | E75: Inter Cars S.A., Poland | F75: Poland | G75: FOB | H75: VR Logistics | I75: 45824 | J75: NH | K75: ONE | L75: Hariom | M75: Gdynia | N75: FOB | O75: ROW | P75: 45828 | Q75: Jun-25
A76: 45829 | B76: Jun | C76: Europe | D76: OOCU9074900 | E76: Agrigear LTD, Ireland | F76: Ireland | G76: FOB | H76: Hind Freight | I76: 45827 | J76: NH | K76: COSCO | L76: Hariom | M76: Dublin | N76: 1500 | O76: ROW | P76: 45829 | Q76: Jun-25
A77: 45828 | B77: Jun | C77: MEA | D77: HASU5056903 | E77: AHMED YOUSIF ABDULHADI ALMAILEM & B, Kuwait | F77: kuwait | G77: CIF | H77: DP World | I77: 45827 | J77: ICD | K77: Maersk | L77: Pegasus | M77: Shuwaikh | N77: 485 | O77: ROW | P77: 45831 | Q77: Jun-25
A78: 45828 | B78: Jun | C78: MEA | D78: TCLU4924320 | E78: AHMED YOUSIF ABDULHADI ALMAILEM & B, Kuwait | F78: kuwait | G78: CIF | H78: DP World | I78: 45827 | J78: ICD | K78: Maersk | L78: Pegasus | M78: Shuwaikh | N78: 485 | O78: ROW | P78: 45831 | Q78: Jun-25
A79: 45830 | B79: Jun | C79: MEA | D79: UETU5629467 | E79: Al Rabee - Sudan | F79: Sudan | G79: FOB | H79: Arikas Logistics | I79: 45828 | J79: NH | K79: PIL | L79: RKY | M79: Port Sudan | O79: ROW | P79: 45831 | Q79: Jun-25
A80: 45830 | B80: Jun | C80: MEA | D80: PCIU9228239 | E80: Al Rabee - Sudan | F80: Sudan | G80: FOB | H80: Arikas Logistics | I80: 45828 | J80: NH | K80: PIL | L80: RKY | M80: Port Sudan | O80: ROW | P80: 45831 | Q80: Jun-25
A81: 45834 | B81: Jun | C81: Europe | D81: TIIU5979278 | E81: Marco Lankes GmbH, Germany | F81: Germany | G81: FOB | H81: Sevenseas Global | I81: 45832 | J81: Tihi | K81: HMM | L81: TRS | M81: Rotterdam | N81: 1200 | O81: ROW | P81: 45834 | Q81: Jun-25
A82: 45834 | B82: Jun | C82: Europe | D82: HMMU6610628 | E82: Marco Lankes GmbH, Germany | F82: Germany | G82: FOB | H82: Sevenseas Global | I82: 45832 | J82: Tihi | K82: HMM | L82: TRS | M82: Rotterdam | N82: 1200 | O82: ROW | P82: 45834 | Q82: Jun-25
A83: 45833 | B83: Jun | C83: Europe | D83: HMMU6256520 | E83: Marco Lankes GmbH, Germany | F83: Germany | G83: FOB | H83: Sevenseas Global | I83: 45832 | J83: Tihi | K83: HMM | L83: TRS | M83: Rotterdam | N83: 1200 | O83: ROW | P83: 45834 | Q83: Jun-25
A84: 45833 | B84: Jun | C84: Europe | D84: HMMU6636427 | E84: Marco Lankes GmbH, Germany | F84: Germany | G84: FOB | H84: Sevenseas Global | I84: 45832 | J84: Tihi | K84: HMM | L84: TRS | M84: Rotterdam | N84: 1200 | O84: ROW | P84: 45834 | Q84: Jun-25
A85: 45833 | B85: Jun | C85: Europe | D85: HMMU6725566 | E85: Marco Lankes GmbH, Germany | F85: Germany | G85: FOB | H85: Sevenseas Global | I85: 45832 | J85: Tihi | K85: HMM | L85: TRS | M85: Rotterdam | N85: 1200 | O85: ROW | P85: 45834 | Q85: Jun-25
A86: 45834 | B86: Jun | C86: Europe | D86: KOCU4217428 | E86: Marco Lankes GmbH, Germany | F86: Germany | G86: FOB | H86: Sevenseas Global | I86: 45832 | J86: Tihi | K86: HMM | L86: TRS | M86: Rotterdam | N86: 1200 | O86: ROW | P86: 45834 | Q86: Jun-25
A87: 45834 | B87: Jun | C87: Europe | D87: TIIU5940635 | E87: Marco Lankes GmbH, Germany | F87: Germany | G87: FOB | H87: Sevenseas Global | I87: 45832 | J87: Tihi | K87: HMM | L87: TRS | M87: Rotterdam | N87: 1200 | O87: ROW | P87: 45835 | Q87: Jun-25
A88: 45834 | B88: Jun | C88: S.A | D88: TCNU5381097 | E88: Rappazzo Neumaticos S.A, Argentina | F88: Argentina | G88: FOB | H88: Tulsidas Khimji | I88: 45832 | J88: NH | K88: CMA | L88: RKY | M88: Buenos Aires | O88: ROW | P88: 45836 | Q88: Jun-25
A89: 45836 | B89: Jun | C89: S.A | D89: TCLU9634766 | E89: REDLLANTAS S.A | F89: columbia | G89: FOB | H89: Mentor Freight | I89: 45835 | J89: ICD | K89: CMA | L89: Pegasus | M89: Buenaventura | O89: ROW | P89: 45836 | Q89: Jun-25
A90: 45835 | B90: Jun | C90: MEA | D90: TCKU6870354 | E90: ROAD FORCE AUTO SPARE PARTS-Sharjah | F90: UAE | G90: FOB | H90: Arikas Logistics | I90: 45835 | J90: ICD | K90: Maersk | L90: Pegasus | M90: Jebel Ali | O90: ROW | P90: 45836 | Q90: Jun-25
A91: 45835 | B91: Jun | C91: MEA | D91: TGBU6304731 | E91: ROAD FORCE AUTO SPARE PARTS-Sharjah | F91: UAE | G91: FOB | H91: Arikas Logistics | I91: 45835 | J91: ICD | K91: Maersk | L91: Pegasus | M91: Jebel Ali | O91: ROW | P91: 45836 | Q91: Jun-25
A92: 45835 | B92: Jun | C92: MEA | D92: SUDU8733370 | E92: ROAD FORCE AUTO SPARE PARTS-Sharjah | F92: UAE | G92: FOB | H92: Arikas Logistics | I92: 45835 | J92: ICD | K92: Maersk | L92: Pegasus | M92: Jebel Ali | O92: ROW | P92: 45836 | Q92: Jun-25
A93: 45836 | B93: Jun | C93: S.A | D93: DFSU7320015 | E93: Correa Tire Distributor Inc, Puerte Rico | F93: Puerto Rico | G93: CIF | H93: Transbox | I93: 45836 | J93: ICD | K93: Hapag | L93: Pegasus | N93: 3600 | O93: ROW | P93: 45838 | Q93: Jun-25
A94: 45838 | B94: Jun | C94: S.A | D94: TCNU7146800 | E94: CPX DISTRIBUIDORA S/A-Navegantes | F94: Brazil | G94: FOB | H94: Skyways Forin | I94: 45836 | J94: NH | K94: MSC | L94: Hariom | M94: Itajai | O94: ROW | P94: 45838 | Q94: Jun-25
A95: 45838 | B95: Jun | C95: Europe | D95: MRSU4149489 | E95: Inter Cars S.A., Poland | F95: Poland | G95: FOB | H95: Master Logitech | I95: 45836 | J95: NH | K95: Maersk | L95: RKY | M95: Gdansk | N95: FOB | O95: ROW | P95: 45838 | Q95: Jun-25
A96: 45838 | B96: Jun | C96: Europe | D96: MRSU3470067 | E96: Inter Cars S.A., Poland | F96: Poland | G96: FOB | H96: Master Logitech | I96: 45836 | J96: NH | K96: Maersk | L96: RKY | M96: Gdansk | N96: FOB | O96: ROW | P96: 45838 | Q96: Jun-25
A97: 45838 | B97: Jun | C97: Europe | D97: MSKU1850832 | E97: Inter Cars S.A., Poland | F97: Poland | G97: FOB | H97: Master Logitech | I97: 45836 | J97: NH | K97: Maersk | L97: RKY | M97: Gdansk | N97: FOB | O97: ROW | P97: 45838 | Q97: Jun-25
A98: 45838 | B98: Jun | C98: Europe | D98: MRKU5885007 | E98: Inter Cars S.A., Poland | F98: Poland | G98: FOB | H98: Master Logitech | I98: 45836 | J98: NH | K98: Maersk | L98: RKY | M98: Gdansk | N98: FOB | O98: ROW | P98: 45838 | Q98: Jun-25
A99: 45840 | B99: Jul | C99: S.A | D99: MSDU5760834 | E99: CPX DISTRIBUIDORA S/A-Navegantes | F99: Brazil | G99: FOB | H99: Skyways Forin | I99: 45838 | J99: NH | K99: MSC | L99: Hariom | M99: Itajai | O99: ROW | P99: NA | Q99: Jul-25
A100: 45847 | B100: Jul | C100: Europe | D100: TCNU4112690 | E100: Inter Cars S.A., Poland | F100: Poland | G100: FOB | H100: VR Logistics | I100: 45845 | J100: NH | K100: ONE | L100: Hariom | M100: GDYNIA | N100: FOB | O100: ROW | P100: NA | Q100: Jul-25
...

Sheet Combination
A1: Financial Year | B1: Quarter | C1: Geography / Region | D1: Country | E1: Customer | F1: POL | G1: POD | H1: Forwarder | I1: INCO Terms | J1: Line / Carrier | K1: Planned Date | L1: Loading Date | M1: Invoice Date | N1: Ocean Freight (USD) | O1: Origin Cost (USD) | P1: Total Cost (USD) | Q1: SortKey
A2: =IFERROR("FY"&TEXT(MOD(IF(MONTH(Sheet1!A2)>=4,YEAR(Sheet1!A2),YEAR(Sheet1!A2)-1),100),"00")&"-"&TEXT(MOD(IF(MONTH(Sheet1!A2)>=4,YEAR(Sheet1!A2),YEAR(Sheet1!A2)-1)+1,100),"00"),"") -> FY25-26 | B2: =IFERROR("Q"&IF(MONTH(Sheet1!A2)>=4,IF(MONTH(Sheet1!A2)<=6,1,IF(MONTH(Sheet1!A2)<=9,2,3)),4),"") -> Q1 | C2: =IFERROR(Sheet1!C2,0) -> MEA | D2: =IFERROR(Sheet1!F2,0) -> DI | E2: =IFERROR(Sheet1!E2,0) -> Nahar Al Ajnas Auto Spre Prts Tradi, Dubai (In) | F2: =IFERROR(IF(UPPER(TRIM(Sheet1!J2))="NH","Nhava Sheva",IF(UPPER(TRIM(Sheet1!J2))="ICD","ICD Dhannad",IF(UPPER(TRIM(Sheet1!J2))="TIHI","ICD Tihi",Sheet1!J2))),0) -> Nhava Sheva | G2: =IFERROR(Sheet1!M2,0) -> Jebel Ali | H2: =IFERROR(Sheet1!H2,0) -> GACIS CARGO | I2: =IFERROR(Sheet1!G2,0) -> FOB | J2: =IFERROR(Sheet1!K2,0) -> InterGlobe Marine | K2: =IFERROR(Sheet1!A2,0) -> 45751 | L2: =IFERROR(Sheet1!I2,0) -> 45750 | M2: =IFERROR(Sheet1!P2,0) -> 45753 | N2: =IFERROR(IF(ISNUMBER(Sheet1!N2),Sheet1!N2,0),0) -> 0 | O2: =IFERROR(IF(TRIM(F2)="Nhava Sheva",SUMPRODUCT((UPPER(TRIM('Origin Costs'!$A$5:$A$44))=UPPER(TRIM(J2)))*'Origin Costs'!$C$5:$C$44),IF(TRIM(F2)="ICD Tihi",SUMPRODUCT((UPPER(TRIM('Origin Costs'!$A$49:$A$88))=UPPER(TRIM(J2)))*'Origin Costs'!$C$49:$C$88),IF(TRIM(F2)="ICD Dhannad",SUMPRODUCT((UPPER(TRIM('Origin Costs'!$A$93:$A$132))=UPPER(TRIM(J2)))*'Origin Costs'!$C$93:$C$132),0))),0) -> 0 | P2: =N2+O2 -> 0 | Q2: =IF(OR(Dashboard!$C$4="All Customers",$E2=Dashboard!$C$4),IF($E2="","",$P2+ROW()/10000000),"")
A3: =IFERROR("FY"&TEXT(MOD(IF(MONTH(Sheet1!A3)>=4,YEAR(Sheet1!A3),YEAR(Sheet1!A3)-1),100),"00")&"-"&TEXT(MOD(IF(MONTH(Sheet1!A3)>=4,YEAR(Sheet1!A3),YEAR(Sheet1!A3)-1)+1,100),"00"),"") -> FY25-26 | B3: =IFERROR("Q"&IF(MONTH(Sheet1!A3)>=4,IF(MONTH(Sheet1!A3)<=6,1,IF(MONTH(Sheet1!A3)<=9,2,3)),4),"") -> Q1 | C3: =IFERROR(Sheet1!C3,0) -> MEA | D3: =IFERROR(Sheet1!F3,0) -> DI | E3: =IFERROR(Sheet1!E3,0) -> Nahar Al Ajnas Auto Spre Prts Tradi, Dubai (In) | F3: =IFERROR(IF(UPPER(TRIM(Sheet1!J3))="NH","Nhava Sheva",IF(UPPER(TRIM(Sheet1!J3))="ICD","ICD Dhannad",IF(UPPER(TRIM(Sheet1!J3))="TIHI","ICD Tihi",Sheet1!J3))),0) -> Nhava Sheva | G3: =IFERROR(Sheet1!M3,0) -> Jebel Ali | H3: =IFERROR(Sheet1!H3,0) -> GACIS CARGO | I3: =IFERROR(Sheet1!G3,0) -> FOB | J3: =IFERROR(Sheet1!K3,0) -> InterGlobe Marine | K3: =IFERROR(Sheet1!A3,0) -> 45751 | L3: =IFERROR(Sheet1!I3,0) -> 45750 | M3: =IFERROR(Sheet1!P3,0) -> 45753 | N3: =IFERROR(IF(ISNUMBER(Sheet1!N3),Sheet1!N3,0),0) -> 0 | O3: =IFERROR(IF(TRIM(F3)="Nhava Sheva",SUMPRODUCT((UPPER(TRIM('Origin Costs'!$A$5:$A$44))=UPPER(TRIM(J3)))*'Origin Costs'!$C$5:$C$44),IF(TRIM(F3)="ICD Tihi",SUMPRODUCT((UPPER(TRIM('Origin Costs'!$A$49:$A$88))=UPPER(TRIM(J3)))*'Origin Costs'!$C$49:$C$88),IF(TRIM(F3)="ICD Dhannad",SUMPRODUCT((UPPER(TRIM('Origin Costs'!$A$93:$A$132))=UPPER(TRIM(J3)))*'Origin Costs'!$C$93:$C$132),0))),0) -> 0 | P3: =N3+O3 -> 0 | Q3: =IF(OR(Dashboard!$C$4="All Customers",$E3=Dashboard!$C$4),IF($E3="","",$P3+ROW()/10000000),"")
A4: =IFERROR("FY"&TEXT(MOD(IF(MONTH(Sheet1!A4)>=4,YEAR(Sheet1!A4),YEAR(Sheet1!A4)-1),100),"00")&"-"&TEXT(MOD(IF(MONTH(Sheet1!A4)>=4,YEAR(Sheet1!A4),YEAR(Sheet1!A4)-1)+1,100),"00"),"") -> FY25-26 | B4: =IFERROR("Q"&IF(MONTH(Sheet1!A4)>=4,IF(MONTH(Sheet1!A4)<=6,1,IF(MONTH(Sheet1!A4)<=9,2,3)),4),"") -> Q1 | C4: =IFERROR(Sheet1!C4,0) -> MEA | D4: =IFERROR(Sheet1!F4,0) -> Afghanistan | E4: =IFERROR(Sheet1!E4,0) -> SHOAIB FAISAL QALANDARI LTD | F4: =IFERROR(IF(UPPER(TRIM(Sheet1!J4))="NH","Nhava Sheva",IF(UPPER(TRIM(Sheet1!J4))="ICD","ICD Dhannad",IF(UPPER(TRIM(Sheet1!J4))="TIHI","ICD Tihi",Sheet1!J4))),0) -> Nhava Sheva | G4: =IFERROR(Sheet1!M4,0) -> Jebel Ali | H4: =IFERROR(Sheet1!H4,0) -> IGM Shipping | I4: =IFERROR(Sheet1!G4,0) -> FOB | J4: =IFERROR(Sheet1!K4,0) -> InterGlobe Marine | K4: =IFERROR(Sheet1!A4,0) -> 45752 | L4: =IFERROR(Sheet1!I4,0) -> 45745 | M4: =IFERROR(Sheet1!P4,0) -> 45754 | N4: =IFERROR(IF(ISNUMBER(Sheet1!N4),Sheet1!N4,0),0) -> 0 | O4: =IFERROR(IF(TRIM(F4)="Nhava Sheva",SUMPRODUCT((UPPER(TRIM('Origin Costs'!$A$5:$A$44))=UPPER(TRIM(J4)))*'Origin Costs'!$C$5:$C$44),IF(TRIM(F4)="ICD Tihi",SUMPRODUCT((UPPER(TRIM('Origin Costs'!$A$49:$A$88))=UPPER(TRIM(J4)))*'Origin Costs'!$C$49:$C$88),IF(TRIM(F4)="ICD Dhannad",SUMPRODUCT((UPPER(TRIM('Origin Costs'!$A$93:$A$132))=UPPER(TRIM(J4)))*'Origin Costs'!$C$93:$C$132),0))),0) -> 0 | P4: =N4+O4 -> 0 | Q4: =IF(OR(Dashboard!$C$4="All Customers",$E4=Dashboard!$C$4),IF($E4="","",$P4+ROW()/10000000),"")
A5: =IFERROR("FY"&TEXT(MOD(IF(MONTH(Sheet1!A5)>=4,YEAR(Sheet1!A5),YEAR(Sheet1!A5)-1),100),"00")&"-"&TEXT(MOD(IF(MONTH(Sheet1!A5)>=4,YEAR(Sheet1!A5),YEAR(Sheet1!A5)-1)+1,100),"00"),"") -> FY25-26 | B5: =IFERROR("Q"&IF(MONTH(Sheet1!A5)>=4,IF(MONTH(Sheet1!A5)<=6,1,IF(MONTH(Sheet1!A5)<=9,2,3)),4),"") -> Q1 | C5: =IFERROR(Sheet1!C5,0) -> MEA | D5: =IFERROR(Sheet1!F5,0) -> DI | E5: =IFERROR(Sheet1!E5,0) -> Nahar Al Ajnas Auto Spre Prts Tradi, Dubai (In) | F5: =IFERROR(IF(UPPER(TRIM(Sheet1!J5))="NH","Nhava Sheva",IF(UPPER(TRIM(Sheet1!J5))="ICD","ICD Dhannad",IF(UPPER(TRIM(Sheet1!J5))="TIHI","ICD Tihi",Sheet1!J5))),0) -> Nhava Sheva | G5: =IFERROR(Sheet1!M5,0) -> Jebel Ali | H5: =IFERROR(Sheet1!H5,0) -> GACIS CARGO | I5: =IFERROR(Sheet1!G5,0) -> FOB | J5: =IFERROR(Sheet1!K5,0) -> InterGlobe Marine | K5: =IFERROR(Sheet1!A5,0) -> 45751 | L5: =IFERROR(Sheet1!I5,0) -> 45750 | M5: =IFERROR(Sheet1!P5,0) -> 45759 | N5: =IFERROR(IF(ISNUMBER(Sheet1!N5),Sheet1!N5,0),0) -> 0 | O5: =IFERROR(IF(TRIM(F5)="Nhava Sheva",SUMPRODUCT((UPPER(TRIM('Origin Costs'!$A$5:$A$44))=UPPER(TRIM(J5)))*'Origin Costs'!$C$5:$C$44),IF(TRIM(F5)="ICD Tihi",SUMPRODUCT((UPPER(TRIM('Origin Costs'!$A$49:$A$88))=UPPER(TRIM(J5)))*'Origin Costs'!$C$49:$C$88),IF(TRIM(F5)="ICD Dhannad",SUMPRODUCT((UPPER(TRIM('Origin Costs'!$A$93:$A$132))=UPPER(TRIM(J5)))*'Origin Costs'!$C$93:$C$132),0))),0) -> 0 | P5: =N5+O5 -> 0 | Q5: =IF(OR(Dashboard!$C$4="All Customers",$E5=Dashboard!$C$4),IF($E5="","",$P5+ROW()/10000000),"")
A6: =IFERROR("FY"&TEXT(MOD(IF(MONTH(Sheet1!A6)>=4,YEAR(Sheet1!A6),YEAR(Sheet1!A6)-1),100),"00")&"-"&TEXT(MOD(IF(MONTH(Sheet1!A6)>=4,YEAR(Sheet1!A6),YEAR(Sheet1!A6)-1)+1,100),"00"),"") -> FY25-26 | B6: =IFERROR("Q"&IF(MONTH(Sheet1!A6)>=4,IF(MONTH(Sheet1!A6)<=6,1,IF(MONTH(Sheet1!A6)<=9,2,3)),4),"") -> Q1 | C6: =IFERROR(Sheet1!C6,0) -> MEA | D6: =IFERROR(Sheet1!F6,0) -> DI | E6: =IFERROR(Sheet1!E6,0) -> Nahar Al Ajnas Auto Spre Prts Tradi, Dubai (In) | F6: =IFERROR(IF(UPPER(TRIM(Sheet1!J6))="NH","Nhava Sheva",IF(UPPER(TRIM(Sheet1!J6))="ICD","ICD Dhannad",IF(UPPER(TRIM(Sheet1!J6))="TIHI","ICD Tihi",Sheet1!J6))),0) -> Nhava Sheva | G6: =IFERROR(Sheet1!M6,0) -> Jebel Ali | H6: =IFERROR(Sheet1!H6,0) -> GACIS CARGO | I6: =IFERROR(Sheet1!G6,0) -> FOB | J6: =IFERROR(Sheet1!K6,0) -> InterGlobe Marine | K6: =IFERROR(Sheet1!A6,0) -> 45751 | L6: =IFERROR(Sheet1!I6,0) -> 45750 | M6: =IFERROR(Sheet1!P6,0) -> 45759 | N6: =IFERROR(IF(ISNUMBER(Sheet1!N6),Sheet1!N6,0),0) -> 0 | O6: =IFERROR(IF(TRIM(F6)="Nhava Sheva",SUMPRODUCT((UPPER(TRIM('Origin Costs'!$A$5:$A$44))=UPPER(TRIM(J6)))*'Origin Costs'!$C$5:$C$44),IF(TRIM(F6)="ICD Tihi",SUMPRODUCT((UPPER(TRIM('Origin Costs'!$A$49:$A$88))=UPPER(TRIM(J6)))*'Origin Costs'!$C$49:$C$88),IF(TRIM(F6)="ICD Dhannad",SUMPRODUCT((UPPER(TRIM('Origin Costs'!$A$93:$A$132))=UPPER(TRIM(J6)))*'Origin Costs'!$C$93:$C$132),0))),0) -> 0 | P6: =N6+O6 -> 0 | Q6: =IF(OR(Dashboard!$C$4="All Customers",$E6=Dashboard!$C$4),IF($E6="","",$P6+ROW()/10000000),"")
A7: =IFERROR("FY"&TEXT(MOD(IF(MONTH(Sheet1!A7)>=4,YEAR(Sheet1!A7),YEAR(Sheet1!A7)-1),100),"00")&"-"&TEXT(MOD(IF(MONTH(Sheet1!A7)>=4,YEAR(Sheet1!A7),YEAR(Sheet1!A7)-1)+1,100),"00"),"") -> FY25-26 | B7: =IFERROR("Q"&IF(MONTH(Sheet1!A7)>=4,IF(MONTH(Sheet1!A7)<=6,1,IF(MONTH(Sheet1!A7)<=9,2,3)),4),"") -> Q1 | C7: =IFERROR(Sheet1!C7,0) -> MEA | D7: =IFERROR(Sheet1!F7,0) -> DI | E7: =IFERROR(Sheet1!E7,0) -> Nahar Al Ajnas Auto Spre Prts Tradi, Dubai (In) | F7: =IFERROR(IF(UPPER(TRIM(Sheet1!J7))="NH","Nhava Sheva",IF(UPPER(TRIM(Sheet1!J7))="ICD","ICD Dhannad",IF(UPPER(TRIM(Sheet1!J7))="TIHI","ICD Tihi",Sheet1!J7))),0) -> Nhava Sheva | G7: =IFERROR(Sheet1!M7,0) -> Jebel Ali | H7: =IFERROR(Sheet1!H7,0) -> GACIS CARGO | I7: =IFERROR(Sheet1!G7,0) -> FOB | J7: =IFERROR(Sheet1!K7,0) -> InterGlobe Marine | K7: =IFERROR(Sheet1!A7,0) -> 45751 | L7: =IFERROR(Sheet1!I7,0) -> 45750 | M7: =IFERROR(Sheet1!P7,0) -> 45759 | N7: =IFERROR(IF(ISNUMBER(Sheet1!N7),Sheet1!N7,0),0) -> 0 | O7: =IFERROR(IF(TRIM(F7)="Nhava Sheva",SUMPRODUCT((UPPER(TRIM('Origin Costs'!$A$5:$A$44))=UPPER(TRIM(J7)))*'Origin Costs'!$C$5:$C$44),IF(TRIM(F7)="ICD Tihi",SUMPRODUCT((UPPER(TRIM('Origin Costs'!$A$49:$A$88))=UPPER(TRIM(J7)))*'Origin Costs'!$C$49:$C$88),IF(TRIM(F7)="ICD Dhannad",SUMPRODUCT((UPPER(TRIM('Origin Costs'!$A$93:$A$132))=UPPER(TRIM(J7)))*'Origin Costs'!$C$93:$C$132),0))),0) -> 0 | P7: =N7+O7 -> 0 | Q7: =IF(OR(Dashboard!$C$4="All Customers",$E7=Dashboard!$C$4),IF($E7="","",$P7+ROW()/10000000),"")
A8: =IFERROR("FY"&TEXT(MOD(IF(MONTH(Sheet1!A8)>=4,YEAR(Sheet1!A8),YEAR(Sheet1!A8)-1),100),"00")&"-"&TEXT(MOD(IF(MONTH(Sheet1!A8)>=4,YEAR(Sheet1!A8),YEAR(Sheet1!A8)-1)+1,100),"00"),"") -> FY25-26 | B8: =IFERROR("Q"&IF(MONTH(Sheet1!A8)>=4,IF(MONTH(Sheet1!A8)<=6,1,IF(MONTH(Sheet1!A8)<=9,2,3)),4),"") -> Q1 | C8: =IFERROR(Sheet1!C8,0) -> S.A. | D8: =IFERROR(Sheet1!F8,0) -> Columbia | E8: =IFERROR(Sheet1!E8,0) -> MULTILLANTAS ZONA LIBRE S.A., Panama | F8: =IFERROR(IF(UPPER(TRIM(Sheet1!J8))="NH","Nhava Sheva",IF(UPPER(TRIM(Sheet1!J8))="ICD","ICD Dhannad",IF(UPPER(TRIM(Sheet1!J8))="TIHI","ICD Tihi",Sheet1!J8))),0) -> Nhava Sheva | G8: =IFERROR(Sheet1!M8,0) -> Buenaventura | H8: =IFERROR(Sheet1!H8,0) -> Pisces shipping | I8: =IFERROR(Sheet1!G8,0) -> FOB | J8: =IFERROR(Sheet1!K8,0) -> CMA | K8: =IFERROR(Sheet1!A8,0) -> 45762 | L8: =IFERROR(Sheet1!I8,0) -> 45761 | M8: =IFERROR(Sheet1!P8,0) -> 45763 | N8: =IFERROR(IF(ISNUMBER(Sheet1!N8),Sheet1!N8,0),0) -> 0 | O8: =IFERROR(IF(TRIM(F8)="Nhava Sheva",SUMPRODUCT((UPPER(TRIM('Origin Costs'!$A$5:$A$44))=UPPER(TRIM(J8)))*'Origin Costs'!$C$5:$C$44),IF(TRIM(F8)="ICD Tihi",SUMPRODUCT((UPPER(TRIM('Origin Costs'!$A$49:$A$88))=UPPER(TRIM(J8)))*'Origin Costs'!$C$49:$C$88),IF(TRIM(F8)="ICD Dhannad",SUMPRODUCT((UPPER(TRIM('Origin Costs'!$A$93:$A$132))=UPPER(TRIM(J8)))*'Origin Costs'!$C$93:$C$132),0))),0) -> 0 | P8: =N8+O8 -> 0 | Q8: =IF(OR(Dashboard!$C$4="All Customers",$E8=Dashboard!$C$4),IF($E8="","",$P8+ROW()/10000000),"")
A9: =IFERROR("FY"&TEXT(MOD(IF(MONTH(Sheet1!A9)>=4,YEAR(Sheet1!A9),YEAR(Sheet1!A9)-1),100),"00")&"-"&TEXT(MOD(IF(MONTH(Sheet1!A9)>=4,YEAR(Sheet1!A9),YEAR(Sheet1!A9)-1)+1,100),"00"),"") -> FY25-26 | B9: =IFERROR("Q"&IF(MONTH(Sheet1!A9)>=4,IF(MONTH(Sheet1!A9)<=6,1,IF(MONTH(Sheet1!A9)<=9,2,3)),4),"") -> Q1 | C9: =IFERROR(Sheet1!C9,0) -> S.A. | D9: =IFERROR(Sheet1!F9,0) -> Columbia | E9: =IFERROR(Sheet1!E9,0) -> MULTILLANTAS ZONA LIBRE S.A., Panama | F9: =IFERROR(IF(UPPER(TRIM(Sheet1!J9))="NH","Nhava Sheva",IF(UPPER(TRIM(Sheet1!J9))="ICD","ICD Dhannad",IF(UPPER(TRIM(Sheet1!J9))="TIHI","ICD Tihi",Sheet1!J9))),0) -> Nhava Sheva | G9: =IFERROR(Sheet1!M9,0) -> Buenaventura | H9: =IFERROR(Sheet1!H9,0) -> Pisces shipping | I9: =IFERROR(Sheet1!G9,0) -> FOB | J9: =IFERROR(Sheet1!K9,0) -> CMA | K9: =IFERROR(Sheet1!A9,0) -> 45762 | L9: =IFERROR(Sheet1!I9,0) -> 45761 | M9: =IFERROR(Sheet1!P9,0) -> 45766 | N9: =IFERROR(IF(ISNUMBER(Sheet1!N9),Sheet1!N9,0),0) -> 0 | O9: =IFERROR(IF(TRIM(F9)="Nhava Sheva",SUMPRODUCT((UPPER(TRIM('Origin Costs'!$A$5:$A$44))=UPPER(TRIM(J9)))*'Origin Costs'!$C$5:$C$44),IF(TRIM(F9)="ICD Tihi",SUMPRODUCT((UPPER(TRIM('Origin Costs'!$A$49:$A$88))=UPPER(TRIM(J9)))*'Origin Costs'!$C$49:$C$88),IF(TRIM(F9)="ICD Dhannad",SUMPRODUCT((UPPER(TRIM('Origin Costs'!$A$93:$A$132))=UPPER(TRIM(J9)))*'Origin Costs'!$C$93:$C$132),0))),0) -> 0 | P9: =N9+O9 -> 0 | Q9: =IF(OR(Dashboard!$C$4="All Customers",$E9=Dashboard!$C$4),IF($E9="","",$P9+ROW()/10000000),"")
A10: =IFERROR("FY"&TEXT(MOD(IF(MONTH(Sheet1!A10)>=4,YEAR(Sheet1!A10),YEAR(Sheet1!A10)-1),100),"00")&"-"&TEXT(MOD(IF(MONTH(Sheet1!A10)>=4,YEAR(Sheet1!A10),YEAR(Sheet1!A10)-1)+1,100),"00"),"") -> FY25-26 | B10: =IFERROR("Q"&IF(MONTH(Sheet1!A10)>=4,IF(MONTH(Sheet1!A10)<=6,1,IF(MONTH(Sheet1!A10)<=9,2,3)),4),"") -> Q1 | C10: =IFERROR(Sheet1!C10,0) -> Europe | D10: =IFERROR(Sheet1!F10,0) -> United Kingdom | E10: =IFERROR(Sheet1!E10,0) -> BA Bush Tyres | F10: =IFERROR(IF(UPPER(TRIM(Sheet1!J10))="NH","Nhava Sheva",IF(UPPER(TRIM(Sheet1!J10))="ICD","ICD Dhannad",IF(UPPER(TRIM(Sheet1!J10))="TIHI","ICD Tihi",Sheet1!J10))),0) -> ICD Dhannad | G10: =IFERROR(Sheet1!M10,0) -> London Gateway | H10: =IFERROR(Sheet1!H10,0) -> Transbox | I10: =IFERROR(Sheet1!G10,0) -> FOB | J10: =IFERROR(Sheet1!K10,0) -> Hapag | K10: =IFERROR(Sheet1!A10,0) -> 45769 | L10: =IFERROR(Sheet1!I10,0) -> 45769 | M10: =IFERROR(Sheet1!P10,0) -> 45768 | N10: =IFERROR(IF(ISNUMBER(Sheet1!N10),Sheet1!N10,0),0) -> 1325 | O10: =IFERROR(IF(TRIM(F10)="Nhava Sheva",SUMPRODUCT((UPPER(TRIM('Origin Costs'!$A$5:$A$44))=UPPER(TRIM(J10)))*'Origin Costs'!$C$5:$C$44),IF(TRIM(F10)="ICD Tihi",SUMPRODUCT((UPPER(TRIM('Origin Costs'!$A$49:$A$88))=UPPER(TRIM(J10)))*'Origin Costs'!$C$49:$C$88),IF(TRIM(F10)="ICD Dhannad",SUMPRODUCT((UPPER(TRIM('Origin Costs'!$A$93:$A$132))=UPPER(TRIM(J10)))*'Origin Costs'!$C$93:$C$132),0))),0) -> 1209.3889 | P10: =N10+O10 -> 2534.3889 | Q10: =IF(OR(Dashboard!$C$4="All Customers",$E10=Dashboard!$C$4),IF($E10="","",$P10+ROW()/10000000),"")
A11: =IFERROR("FY"&TEXT(MOD(IF(MONTH(Sheet1!A11)>=4,YEAR(Sheet1!A11),YEAR(Sheet1!A11)-1),100),"00")&"-"&TEXT(MOD(IF(MONTH(Sheet1!A11)>=4,YEAR(Sheet1!A11),YEAR(Sheet1!A11)-1)+1,100),"00"),"") -> FY25-26 | B11: =IFERROR("Q"&IF(MONTH(Sheet1!A11)>=4,IF(MONTH(Sheet1!A11)<=6,1,IF(MONTH(Sheet1!A11)<=9,2,3)),4),"") -> Q1 | C11: =IFERROR(Sheet1!C11,0) -> S.A. | D11: =IFERROR(Sheet1!F11,0) -> Panama | E11: =IFERROR(Sheet1!E11,0) -> MULTILLANTAS ZONA LIBRE S.A., Panama | F11: =IFERROR(IF(UPPER(TRIM(Sheet1!J11))="NH","Nhava Sheva",IF(UPPER(TRIM(Sheet1!J11))="ICD","ICD Dhannad",IF(UPPER(TRIM(Sheet1!J11))="TIHI","ICD Tihi",Sheet1!J11))),0) -> Nhava Sheva | G11: =IFERROR(Sheet1!M11,0) -> Manzanilo | H11: =IFERROR(Sheet1!H11,0) -> Kotak Global | I11: =IFERROR(Sheet1!G11,0) -> CIF | J11: =IFERROR(Sheet1!K11,0) -> Evergreen | K11: =IFERROR(Sheet1!A11,0) -> 45768 | L11: =IFERROR(Sheet1!I11,0) -> 45766 | M11: =IFERROR(Sheet1!P11,0) -> 45768 | N11: =IFERROR(IF(ISNUMBER(Sheet1!N11),Sheet1!N11,0),0) -> 3350 | O11: =IFERROR(IF(TRIM(F11)="Nhava Sheva",SUMPRODUCT((UPPER(TRIM('Origin Costs'!$A$5:$A$44))=UPPER(TRIM(J11)))*'Origin Costs'!$C$5:$C$44),IF(TRIM(F11)="ICD Tihi",SUMPRODUCT((UPPER(TRIM('Origin Costs'!$A$49:$A$88))=UPPER(TRIM(J11)))*'Origin Costs'!$C$49:$C$88),IF(TRIM(F11)="ICD Dhannad",SUMPRODUCT((UPPER(TRIM('Origin Costs'!$A$93:$A$132))=UPPER(TRIM(J11)))*'Origin Costs'!$C$93:$C$132),0))),0) -> 0 | P11: =N11+O11 -> 3350 | Q11: =IF(OR(Dashboard!$C$4="All Customers",$E11=Dashboard!$C$4),IF($E11="","",$P11+ROW()/10000000),"")
A12: =IFERROR("FY"&TEXT(MOD(IF(MONTH(Sheet1!A12)>=4,YEAR(Sheet1!A12),YEAR(Sheet1!A12)-1),100),"00")&"-"&TEXT(MOD(IF(MONTH(Sheet1!A12)>=4,YEAR(Sheet1!A12),YEAR(Sheet1!A12)-1)+1,100),"00"),"") -> FY25-26 | B12: =IFERROR("Q"&IF(MONTH(Sheet1!A12)>=4,IF(MONTH(Sheet1!A12)<=6,1,IF(MONTH(Sheet1!A12)<=9,2,3)),4),"") -> Q1 | C12: =IFERROR(Sheet1!C12,0) -> Europe | D12: =IFERROR(Sheet1!F12,0) -> Spain | E12: =IFERROR(Sheet1!E12,0) -> TRADELUC FZE LLC, Spain | F12: =IFERROR(IF(UPPER(TRIM(Sheet1!J12))="NH","Nhava Sheva",IF(UPPER(TRIM(Sheet1!J12))="ICD","ICD Dhannad",IF(UPPER(TRIM(Sheet1!J12))="TIHI","ICD Tihi",Sheet1!J12))),0) -> Nhava Sheva | G12: =IFERROR(Sheet1!M12,0) -> Valencia | H12: =IFERROR(Sheet1!H12,0) -> Active Shipping | I12: =IFERROR(Sheet1!G12,0) -> FOB | J12: =IFERROR(Sheet1!K12,0) -> Hyundai | K12: =IFERROR(Sheet1!A12,0) -> 45767 | L12: =IFERROR(Sheet1!I12,0) -> 45765 | M12: =IFERROR(Sheet1!P12,0) -> 45768 | N12: =IFERROR(IF(ISNUMBER(Sheet1!N12),Sheet1!N12,0),0) -> 0 | O12: =IFERROR(IF(TRIM(F12)="Nhava Sheva",SUMPRODUCT((UPPER(TRIM('Origin Costs'!$A$5:$A$44))=UPPER(TRIM(J12)))*'Origin Costs'!$C$5:$C$44),IF(TRIM(F12)="ICD Tihi",SUMPRODUCT((UPPER(TRIM('Origin Costs'!$A$49:$A$88))=UPPER(TRIM(J12)))*'Origin Costs'!$C$49:$C$88),IF(TRIM(F12)="ICD Dhannad",SUMPRODUCT((UPPER(TRIM('Origin Costs'!$A$93:$A$132))=UPPER(TRIM(J12)))*'Origin Costs'!$C$93:$C$132),0))),0) -> 0 | P12: =N12+O12 -> 0 | Q12: =IF(OR(Dashboard!$C$4="All Customers",$E12=Dashboard!$C$4),IF($E12="","",$P12+ROW()/10000000),"")
A13: =IFERROR("FY"&TEXT(MOD(IF(MONTH(Sheet1!A13)>=4,YEAR(Sheet1!A13),YEAR(Sheet1!A13)-1),100),"00")&"-"&TEXT(MOD(IF(MONTH(Sheet1!A13)>=4,YEAR(Sheet1!A13),YEAR(Sheet1!A13)-1)+1,100),"00"),"") -> FY25-26 | B13: =IFERROR("Q"&IF(MONTH(Sheet1!A13)>=4,IF(MONTH(Sheet1!A13)<=6,1,IF(MONTH(Sheet1!A13)<=9,2,3)),4),"") -> Q1 | C13: =IFERROR(Sheet1!C13,0) -> MEA | D13: =IFERROR(Sheet1!F13,0) -> Sudan | E13: =IFERROR(Sheet1!E13,0) -> Al Rabee - Sudan | F13: =IFERROR(IF(UPPER(TRIM(Sheet1!J13))="NH","Nhava Sheva",IF(UPPER(TRIM(Sheet1!J13))="ICD","ICD Dhannad",IF(UPPER(TRIM(Sheet1!J13))="TIHI","ICD Tihi",Sheet1!J13))),0) -> Nhava Sheva | G13: =IFERROR(Sheet1!M13,0) -> Sudan Port | H13: =IFERROR(Sheet1!H13,0) -> Hind Freight | I13: =IFERROR(Sheet1!G13,0) -> CIF | J13: =IFERROR(Sheet1!K13,0) -> Transmar | K13: =IFERROR(Sheet1!A13,0) -> 45768 | L13: =IFERROR(Sheet1!I13,0) -> 45766 | M13: =IFERROR(Sheet1!P13,0) -> 45769 | N13: =IFERROR(IF(ISNUMBER(Sheet1!N13),Sheet1!N13,0),0) -> 2050 | O13: =IFERROR(IF(TRIM(F13)="Nhava Sheva",SUMPRODUCT((UPPER(TRIM('Origin Costs'!$A$5:$A$44))=UPPER(TRIM(J13)))*'Origin Costs'!$C$5:$C$44),IF(TRIM(F13)="ICD Tihi",SUMPRODUCT((UPPER(TRIM('Origin Costs'!$A$49:$A$88))=UPPER(TRIM(J13)))*'Origin Costs'!$C$49:$C$88),IF(TRIM(F13)="ICD Dhannad",SUMPRODUCT((UPPER(TRIM('Origin Costs'!$A$93:$A$132))=UPPER(TRIM(J13)))*'Origin Costs'!$C$93:$C$132),0))),0) -> 0 | P13: =N13+O13 -> 2050 | Q13: =IF(OR(Dashboard!$C$4="All Customers",$E13=Dashboard!$C$4),IF($E13="","",$P13+ROW()/10000000),"")
... A628: =IFERROR("FY"&TEXT(MOD(IF(MONTH(Sheet1!A628)>=4,YEAR(Sheet1!A628),YEAR(Sheet1!A628)-1),100),"00")&"-"&TEXT(MOD(IF(MONTH(Sheet1!A628)>=4,YEAR(Sheet1!A628),YEAR(Sheet1!A628)-1)+1,100),"00"),"") -> FY26-27 | B628: =IFERROR("Q"&IF(MONTH(Sheet1!A628)>=4,IF(MONTH(Sheet1!A628)<=6,1,IF(MONTH(Sheet1!A628)<=9,2,3)),4),"") -> Q1 | C628: =IFERROR(Sheet1!C628,0) -> ISC | D628: =IFERROR(Sheet1!F628,0) -> Sri Lanka | E628: =IFERROR(Sheet1!E628,0) -> Supergrip International, Srilanka | F628: =IFERROR(IF(UPPER(TRIM(Sheet1!J628))="NH","Nhava Sheva",IF(UPPER(TRIM(Sheet1!J628))="ICD","ICD Dhannad",IF(UPPER(TRIM(Sheet1!J628))="TIHI","ICD Tihi",Sheet1!J628))),0) -> Nhava Sheva | G628: =IFERROR(Sheet1!M628,0) -> Colombo | H628: =IFERROR(Sheet1!H628,0) -> UP4 International | I628: =IFERROR(Sheet1!G628,0) -> FOB | J628: =IFERROR(Sheet1!K628,0) -> OOCL | K628: =IFERROR(Sheet1!A628,0) -> 46173 | L628: =IFERROR(Sheet1!I628,0) -> 46170 | M628: =IFERROR(Sheet1!P628,0) -> NA | N628: =IFERROR(IF(ISNUMBER(Sheet1!N628),Sheet1!N628,0),0) -> 0 | O628: =IFERROR(IF(TRIM(F628)="Nhava Sheva",SUMPRODUCT((UPPER(TRIM('Origin Costs'!$A$5:$A$44))=UPPER(TRIM(J628)))*'Origin Costs'!$C$5:$C$44),IF(TRIM(F628)="ICD Tihi",SUMPRODUCT((UPPER(TRIM('Origin Costs'!$A$49:$A$88))=UPPER(TRIM(J628)))*'Origin Costs'!$C$49:$C$88),IF(TRIM(F628)="ICD Dhannad",SUMPRODUCT((UPPER(TRIM('Origin Costs'!$A$93:$A$132))=UPPER(TRIM(J628)))*'Origin Costs'!$C$93:$C$132),0))),0) -> 0 | P628: =N628+O628 -> 0 | Q628: =IF(OR(Dashboard!$C$4="All Customers",$E628=Dashboard!$C$4),IF($E628="","",$P628+ROW()/10000000),"")
Q629: =IF(OR(Dashboard!$C$4="All Customers",$E629=Dashboard!$C$4),IF($E629="","",$P629+ROW()/10000000),"")
Q630: =IF(OR(Dashboard!$C$4="All Customers",$E630=Dashboard!$C$4),IF($E630="","",$P630+ROW()/10000000),"")
Q631: =IF(OR(Dashboard!$C$4="All Customers",$E631=Dashboard!$C$4),IF($E631="","",$P631+ROW()/10000000),"")
Q632: =IF(OR(Dashboard!$C$4="All Customers",$E632=Dashboard!$C$4),IF($E632="","",$P632+ROW()/10000000),"")
Q633: =IF(OR(Dashboard!$C$4="All Customers",$E633=Dashboard!$C$4),IF($E633="","",$P633+ROW()/10000000),"")
Q634: =IF(OR(Dashboard!$C$4="All Customers",$E634=Dashboard!$C$4),IF($E634="","",$P634+ROW()/10000000),"")
Q635: =IF(OR(Dashboard!$C$4="All Customers",$E635=Dashboard!$C$4),IF($E635="","",$P635+ROW()/10000000),"")
Q636: =IF(OR(Dashboard!$C$4="All Customers",$E636=Dashboard!$C$4),IF($E636="","",$P636+ROW()/10000000),"")
Q637: =IF(OR(Dashboard!$C$4="All Customers",$E637=Dashboard!$C$4),IF($E637="","",$P637+ROW()/10000000),"")
Q638: =IF(OR(Dashboard!$C$4="All Customers",$E638=Dashboard!$C$4),IF($E638="","",$P638+ROW()/10000000),"")
Q639: =IF(OR(Dashboard!$C$4="All Customers",$E639=Dashboard!$C$4),IF($E639="","",$P639+ROW()/10000000),"")
Q640: =IF(OR(Dashboard!$C$4="All Customers",$E640=Dashboard!$C$4),IF($E640="","",$P640+ROW()/10000000),"")
... Q2628: =IF(OR(Dashboard!$C$4="All Customers",$E2628=Dashboard!$C$4),IF($E2628="","",$P2628+ROW()/10000000),"")

Sheet Helpers
A1: Customer
A2: All Customers | B2: {=IFERROR(SMALL(IF(IF(Dashboard!$C$5="",TRUE(),ISNUMBER(SEARCH(Dashboard!$C$5,$A$2:$A$202))),ROW($A$2:$A$202)-ROW($A$2)+1),ROW()-ROW($B$2)+1),"")} -> 1 | C2: =IFERROR(INDEX($A$2:$A$202,$B2),"") -> All Customers
A3: {=IFERROR(INDEX(Combination!$E$2:$E$2628,MATCH(0,COUNTIF($A$2:A2,Combination!$E$2:$E$2628)+IF(Combination!$E$2:$E$2628="",1,0),0)),"")} -> Nahar Al Ajnas Auto Spre Prts Tradi, Dubai (In) | B3: {=IFERROR(SMALL(IF(IF(Dashboard!$C$5="",TRUE(),ISNUMBER(SEARCH(Dashboard!$C$5,$A$2:$A$202))),ROW($A$2:$A$202)-ROW($A$2)+1),ROW()-ROW($B$2)+1),"")} -> 2 | C3: =IFERROR(INDEX($A$2:$A$202,$B3),"") -> Nahar Al Ajnas Auto Spre Prts Tradi, Dubai (In)
A4: {=IFERROR(INDEX(Combination!$E$2:$E$2628,MATCH(0,COUNTIF($A$2:A3,Combination!$E$2:$E$2628)+IF(Combination!$E$2:$E$2628="",1,0),0)),"")} -> SHOAIB FAISAL QALANDARI LTD | B4: {=IFERROR(SMALL(IF(IF(Dashboard!$C$5="",TRUE(),ISNUMBER(SEARCH(Dashboard!$C$5,$A$2:$A$202))),ROW($A$2:$A$202)-ROW($A$2)+1),ROW()-ROW($B$2)+1),"")} -> 3 | C4: =IFERROR(INDEX($A$2:$A$202,$B4),"") -> SHOAIB FAISAL QALANDARI LTD
A5: {=IFERROR(INDEX(Combination!$E$2:$E$2628,MATCH(0,COUNTIF($A$2:A4,Combination!$E$2:$E$2628)+IF(Combination!$E$2:$E$2628="",1,0),0)),"")} -> MULTILLANTAS ZONA LIBRE S.A., Panama | B5: {=IFERROR(SMALL(IF(IF(Dashboard!$C$5="",TRUE(),ISNUMBER(SEARCH(Dashboard!$C$5,$A$2:$A$202))),ROW($A$2:$A$202)-ROW($A$2)+1),ROW()-ROW($B$2)+1),"")} -> 4 | C5: =IFERROR(INDEX($A$2:$A$202,$B5),"") -> MULTILLANTAS ZONA LIBRE S.A., Panama
A6: {=IFERROR(INDEX(Combination!$E$2:$E$2628,MATCH(0,COUNTIF($A$2:A5,Combination!$E$2:$E$2628)+IF(Combination!$E$2:$E$2628="",1,0),0)),"")} -> BA Bush Tyres | B6: {=IFERROR(SMALL(IF(IF(Dashboard!$C$5="",TRUE(),ISNUMBER(SEARCH(Dashboard!$C$5,$A$2:$A$202))),ROW($A$2:$A$202)-ROW($A$2)+1),ROW()-ROW($B$2)+1),"")} -> 5 | C6: =IFERROR(INDEX($A$2:$A$202,$B6),"") -> BA Bush Tyres
A7: {=IFERROR(INDEX(Combination!$E$2:$E$2628,MATCH(0,COUNTIF($A$2:A6,Combination!$E$2:$E$2628)+IF(Combination!$E$2:$E$2628="",1,0),0)),"")} -> TRADELUC FZE LLC, Spain | B7: {=IFERROR(SMALL(IF(IF(Dashboard!$C$5="",TRUE(),ISNUMBER(SEARCH(Dashboard!$C$5,$A$2:$A$202))),ROW($A$2:$A$202)-ROW($A$2)+1),ROW()-ROW($B$2)+1),"")} -> 6 | C7: =IFERROR(INDEX($A$2:$A$202,$B7),"") -> TRADELUC FZE LLC, Spain
A8: {=IFERROR(INDEX(Combination!$E$2:$E$2628,MATCH(0,COUNTIF($A$2:A7,Combination!$E$2:$E$2628)+IF(Combination!$E$2:$E$2628="",1,0),0)),"")} -> Al Rabee - Sudan | B8: {=IFERROR(SMALL(IF(IF(Dashboard!$C$5="",TRUE(),ISNUMBER(SEARCH(Dashboard!$C$5,$A$2:$A$202))),ROW($A$2:$A$202)-ROW($A$2)+1),ROW()-ROW($B$2)+1),"")} -> 7 | C8: =IFERROR(INDEX($A$2:$A$202,$B8),"") -> Al Rabee - Sudan
A9: {=IFERROR(INDEX(Combination!$E$2:$E$2628,MATCH(0,COUNTIF($A$2:A8,Combination!$E$2:$E$2628)+IF(Combination!$E$2:$E$2628="",1,0),0)),"")} -> CPX DISTRIBUIDORA S/A-Suape | B9: {=IFERROR(SMALL(IF(IF(Dashboard!$C$5="",TRUE(),ISNUMBER(SEARCH(Dashboard!$C$5,$A$2:$A$202))),ROW($A$2:$A$202)-ROW($A$2)+1),ROW()-ROW($B$2)+1),"")} -> 8 | C9: =IFERROR(INDEX($A$2:$A$202,$B9),"") -> CPX DISTRIBUIDORA S/A-Suape
A10: {=IFERROR(INDEX(Combination!$E$2:$E$2628,MATCH(0,COUNTIF($A$2:A9,Combination!$E$2:$E$2628)+IF(Combination!$E$2:$E$2628="",1,0),0)),"")} -> CPX DISTRIBUIDORA S/A-Itajai | B10: {=IFERROR(SMALL(IF(IF(Dashboard!$C$5="",TRUE(),ISNUMBER(SEARCH(Dashboard!$C$5,$A$2:$A$202))),ROW($A$2:$A$202)-ROW($A$2)+1),ROW()-ROW($B$2)+1),"")} -> 9 | C10: =IFERROR(INDEX($A$2:$A$202,$B10),"") -> CPX DISTRIBUIDORA S/A-Itajai
A11: {=IFERROR(INDEX(Combination!$E$2:$E$2628,MATCH(0,COUNTIF($A$2:A10,Combination!$E$2:$E$2628)+IF(Combination!$E$2:$E$2628="",1,0),0)),"")} -> Marco Lankes GmbH, Germany | B11: {=IFERROR(SMALL(IF(IF(Dashboard!$C$5="",TRUE(),ISNUMBER(SEARCH(Dashboard!$C$5,$A$2:$A$202))),ROW($A$2:$A$202)-ROW($A$2)+1),ROW()-ROW($B$2)+1),"")} -> 10 | C11: =IFERROR(INDEX($A$2:$A$202,$B11),"") -> Marco Lankes GmbH, Germany
A12: {=IFERROR(INDEX(Combination!$E$2:$E$2628,MATCH(0,COUNTIF($A$2:A11,Combination!$E$2:$E$2628)+IF(Combination!$E$2:$E$2628="",1,0),0)),"")} -> AL-DYAR AL-KHADRAA TIRE AND BATTERY, Iraq | B12: {=IFERROR(SMALL(IF(IF(Dashboard!$C$5="",TRUE(),ISNUMBER(SEARCH(Dashboard!$C$5,$A$2:$A$202))),ROW($A$2:$A$202)-ROW($A$2)+1),ROW()-ROW($B$2)+1),"")} -> 11 | C12: =IFERROR(INDEX($A$2:$A$202,$B12),"") -> AL-DYAR AL-KHADRAA TIRE AND BATTERY, Iraq
A13: {=IFERROR(INDEX(Combination!$E$2:$E$2628,MATCH(0,COUNTIF($A$2:A12,Combination!$E$2:$E$2628)+IF(Combination!$E$2:$E$2628="",1,0),0)),"")} -> Agrigear LTD, Ireland | B13: {=IFERROR(SMALL(IF(IF(Dashboard!$C$5="",TRUE(),ISNUMBER(SEARCH(Dashboard!$C$5,$A$2:$A$202))),ROW($A$2:$A$202)-ROW($A$2)+1),ROW()-ROW($B$2)+1),"")} -> 12 | C13: =IFERROR(INDEX($A$2:$A$202,$B13),"") -> Agrigear LTD, Ireland
A14: {=IFERROR(INDEX(Combination!$E$2:$E$2628,MATCH(0,COUNTIF($A$2:A13,Combination!$E$2:$E$2628)+IF(Combination!$E$2:$E$2628="",1,0),0)),"")} -> Inter Cars S.A., Poland | B14: {=IFERROR(SMALL(IF(IF(Dashboard!$C$5="",TRUE(),ISNUMBER(SEARCH(Dashboard!$C$5,$A$2:$A$202))),ROW($A$2:$A$202)-ROW($A$2)+1),ROW()-ROW($B$2)+1),"")} -> 13 | C14: =IFERROR(INDEX($A$2:$A$202,$B14),"") -> Inter Cars S.A., Poland
... A202: {=IFERROR(INDEX(Combination!$E$2:$E$2628,MATCH(0,COUNTIF($A$2:A201,Combination!$E$2:$E$2628)+IF(Combination!$E$2:$E$2628="",1,0),0)),"")} | B202: {=IFERROR(SMALL(IF(IF(Dashboard!$C$5="",TRUE(),ISNUMBER(SEARCH(Dashboard!$C$5,$A$2:$A$202))),ROW($A$2:$A$202)-ROW($A$2)+1),ROW()-ROW($B$2)+1),"")} -> 201 | C202: =IFERROR(INDEX($A$2:$A$202,$B202),"")
